[
  {
    "date": "2026-06-27",
    "departDate": "2026-10-28",
    "returnDate": "2026-11-16",
    "price": 853.0,
    "source": "googleflights",
    "airlines": [
      "Qatar Airways, JAL"
    ],
    "stopsOut": 1,
    "stopsIn": null
  },
  {
    "date": "2026-06-27",
    "departDate": "2026-11-13",
    "returnDate": "2026-11-30",
    "price": 883.0,
    "source": "googleflights",
    "airlines": [
      "Qatar Airways, JAL"
    ],
    "stopsOut": 1,
    "stopsIn": null
  },
  {
    "date": "2026-06-27",
    "departDate": "2026-11-13",
    "returnDate": "2026-11-30",
    "price": 889.0,
    "source": "googleflights",
    "airlines": [
      "Emirates"
    ],
    "stopsOut": 1,
    "stopsIn": null
  },
  {
    "date": "2026-06-27",
    "departDate": "2026-10-28",
    "returnDate": "2026-11-16",
    "price": 977.0,
    "source": "googleflights",
    "airlines": [
      "Qatar Airways"
    ],
    "stopsOut": 1,
    "stopsIn": null
  },
  {
    "date": "2026-06-27",
    "departDate": "2026-10-28",
    "returnDate": "2026-11-16",
    "price": 1159.0,
    "source": "googleflights",
    "airlines": [
      "China Southern"
    ],
    "stopsOut": 1,
    "stopsIn": null
  },
  {
    "date": "2026-06-27",
    "departDate": "2026-10-28",
    "returnDate": "2026-11-16",
    "price": 1161.0,
    "source": "googleflights",
    "airlines": [
      "China Airlines"
    ],
    "stopsOut": 1,
    "stopsIn": null
  },
  {
    "date": "2026-06-27",
    "departDate": "2026-10-07",
    "returnDate": "2026-10-26",
    "price": 1317.0,
    "source": "googleflights",
    "airlines": [
      "Qatar Airways"
    ],
    "stopsOut": 1,
    "stopsIn": null
  },
  {
    "date": "2026-06-27",
    "departDate": "2026-10-07",
    "returnDate": "2026-10-26",
    "price": 1374.0,
    "source": "googleflights",
    "airlines": [
      "Lufthansa, ITA"
    ],
    "stopsOut": 2,
    "stopsIn": null
  },
  {
    "date": "2026-06-27",
    "departDate": "2026-10-07",
    "returnDate": "2026-10-26",
    "price": 1391.0,
    "source": "googleflights",
    "airlines": [
      "China Southern"
    ],
    "stopsOut": 1,
    "stopsIn": null
  },
  {
    "date": "2026-06-28",
    "departDate": "2026-10-28",
    "returnDate": "2026-11-16",
    "price": 853.0,
    "source": "googleflights",
    "airlines": [
      "Qatar Airways, JAL"
    ],
    "stopsOut": 1,
    "stopsIn": null
  },
  {
    "date": "2026-06-28",
    "departDate": "2026-11-13",
    "returnDate": "2026-11-30",
    "price": 883.0,
    "source": "googleflights",
    "airlines": [
      "Qatar Airways, JAL"
    ],
    "stopsOut": 1,
    "stopsIn": null
  },
  {
    "date": "2026-06-28",
    "departDate": "2026-11-13",
    "returnDate": "2026-11-30",
    "price": 889.0,
    "source": "googleflights",
    "airlines": [
      "Emirates"
    ],
    "stopsOut": 1,
    "stopsIn": null
  },
  {
    "date": "2026-06-28",
    "departDate": "2026-10-28",
    "returnDate": "2026-11-16",
    "price": 966.0,
    "source": "googleflights",
    "airlines": [
      "Qatar Airways"
    ],
    "stopsOut": 1,
    "stopsIn": null
  },
  {
    "date": "2026-06-28",
    "departDate": "2026-10-28",
    "returnDate": "2026-11-16",
    "price": 1159.0,
    "source": "googleflights",
    "airlines": [
      "China Southern"
    ],
    "stopsOut": 1,
    "stopsIn": null
  },
  {
    "date": "2026-06-28",
    "departDate": "2026-10-28",
    "returnDate": "2026-11-16",
    "price": 1161.0,
    "source": "googleflights",
    "airlines": [
      "China Airlines"
    ],
    "stopsOut": 1,
    "stopsIn": null
  },
  {
    "date": "2026-06-28",
    "departDate": "2026-10-07",
    "returnDate": "2026-10-26",
    "price": 1317.0,
    "source": "googleflights",
    "airlines": [
      "Qatar Airways"
    ],
    "stopsOut": 1,
    "stopsIn": null
  },
  {
    "date": "2026-06-28",
    "departDate": "2026-10-07",
    "returnDate": "2026-10-26",
    "price": 1374.0,
    "source": "googleflights",
    "airlines": [
      "Lufthansa, ITA"
    ],
    "stopsOut": 2,
    "stopsIn": null
  },
  {
    "date": "2026-06-28",
    "departDate": "2026-10-07",
    "returnDate": "2026-10-26",
    "price": 1391.0,
    "source": "googleflights",
    "airlines": [
      "China Southern"
    ],
    "stopsOut": 1,
    "stopsIn": null
  },
  {
    "date": "2026-06-29",
    "departDate": "2026-11-13",
    "returnDate": "2026-11-30",
    "price": 873.0,
    "source": "googleflights",
    "airlines": [
      "Qatar Airways, JAL"
    ],
    "stopsOut": 1,
    "stopsIn": null
  },
  {
    "date": "2026-06-29",
    "departDate": "2026-11-13",
    "returnDate": "2026-11-30",
    "price": 889.0,
    "source": "googleflights",
    "airlines": [
      "Emirates"
    ],
    "stopsOut": 1,
    "stopsIn": null
  },
  {
    "date": "2026-06-29",
    "departDate": "2026-10-23",
    "returnDate": "2026-11-09",
    "price": 1140.0,
    "source": "googleflights",
    "airlines": [
      "Qatar Airways"
    ],
    "stopsOut": 1,
    "stopsIn": null
  },
  {
    "date": "2026-06-29",
    "departDate": "2026-10-23",
    "returnDate": "2026-11-09",
    "price": 1142.0,
    "source": "googleflights",
    "airlines": [
      "Qatar Airways"
    ],
    "stopsOut": 1,
    "stopsIn": null
  },
  {
    "date": "2026-06-29",
    "departDate": "2026-10-23",
    "returnDate": "2026-11-09",
    "price": 1256.0,
    "source": "googleflights",
    "airlines": [
      "China Airlines"
    ],
    "stopsOut": 1,
    "stopsIn": null
  },
  {
    "date": "2026-06-29",
    "departDate": "2026-10-02",
    "returnDate": "2026-10-19",
    "price": 1376.0,
    "source": "googleflights",
    "airlines": [
      "Air France"
    ],
    "stopsOut": 1,
    "stopsIn": null
  },
  {
    "date": "2026-06-29",
    "departDate": "2026-10-02",
    "returnDate": "2026-10-19",
    "price": 1460.0,
    "source": "googleflights",
    "airlines": [
      "Gulf Air, Philippine Airlines"
    ],
    "stopsOut": 2,
    "stopsIn": null
  },
  {
    "date": "2026-06-29",
    "departDate": "2026-10-02",
    "returnDate": "2026-10-19",
    "price": 1486.0,
    "source": "googleflights",
    "airlines": [
      "Gulf Air, Philippine Airlines"
    ],
    "stopsOut": 2,
    "stopsIn": null
  },
  {
    "date": "2026-06-29",
    "departDate": "2026-10-02",
    "returnDate": "2026-10-19",
    "price": 1533.0,
    "source": "googleflights",
    "airlines": [
      "Emirates"
    ],
    "stopsOut": 1,
    "stopsIn": null
  },
  {
    "date": "2026-06-30",
    "departDate": "2026-11-13",
    "returnDate": "2026-11-30",
    "price": 873.0,
    "source": "googleflights",
    "airlines": [
      "Qatar Airways, JAL"
    ],
    "stopsOut": 1,
    "stopsIn": null
  },
  {
    "date": "2026-06-30",
    "departDate": "2026-11-13",
    "returnDate": "2026-11-30",
    "price": 889.0,
    "source": "googleflights",
    "airlines": [
      "Emirates"
    ],
    "stopsOut": 1,
    "stopsIn": null
  },
  {
    "date": "2026-06-30",
    "departDate": "2026-11-13",
    "returnDate": "2026-11-30",
    "price": 922.0,
    "source": "googleflights",
    "airlines": [
      "Emirates"
    ],
    "stopsOut": 1,
    "stopsIn": null
  },
  {
    "date": "2026-06-30",
    "departDate": "2026-10-23",
    "returnDate": "2026-11-09",
    "price": 1140.0,
    "source": "googleflights",
    "airlines": [
      "Qatar Airways"
    ],
    "stopsOut": 1,
    "stopsIn": null
  },
  {
    "date": "2026-06-30",
    "departDate": "2026-10-23",
    "returnDate": "2026-11-09",
    "price": 1142.0,
    "source": "googleflights",
    "airlines": [
      "Qatar Airways"
    ],
    "stopsOut": 1,
    "stopsIn": null
  },
  {
    "date": "2026-06-30",
    "departDate": "2026-10-23",
    "returnDate": "2026-11-09",
    "price": 1154.0,
    "source": "googleflights",
    "airlines": [
      "Lufthansa, ITA"
    ],
    "stopsOut": 2,
    "stopsIn": null
  },
  {
    "date": "2026-07-01",
    "departDate": "2026-10-23",
    "returnDate": "2026-11-09",
    "price": 1188.0,
    "source": "googleflights",
    "airlines": [
      "Qatar Airways"
    ],
    "stopsOut": 1,
    "stopsIn": null
  },
  {
    "date": "2026-07-01",
    "departDate": "2026-10-23",
    "returnDate": "2026-11-09",
    "price": 1272.0,
    "source": "googleflights",
    "airlines": [
      "Finnair"
    ],
    "stopsOut": 1,
    "stopsIn": null
  },
  {
    "date": "2026-07-01",
    "departDate": "2026-10-23",
    "returnDate": "2026-11-09",
    "price": 1330.0,
    "source": "googleflights",
    "airlines": [
      "China Airlines"
    ],
    "stopsOut": 1,
    "stopsIn": null
  },
  {
    "date": "2026-07-02",
    "departDate": "2026-11-13",
    "returnDate": "2026-11-30",
    "price": 885.0,
    "source": "googleflights",
    "airlines": [
      "Qatar Airways, JAL"
    ],
    "stopsOut": 1,
    "stopsIn": null
  },
  {
    "date": "2026-07-02",
    "departDate": "2026-11-13",
    "returnDate": "2026-11-30",
    "price": 932.0,
    "source": "googleflights",
    "airlines": [
      "Emirates"
    ],
    "stopsOut": 1,
    "stopsIn": null
  },
  {
    "date": "2026-07-02",
    "departDate": "2026-11-13",
    "returnDate": "2026-11-30",
    "price": 1049.0,
    "source": "googleflights",
    "airlines": [
      "Emirates"
    ],
    "stopsOut": 1,
    "stopsIn": null
  },
  {
    "date": "2026-07-02",
    "departDate": "2026-10-23",
    "returnDate": "2026-11-09",
    "price": 1186.0,
    "source": "googleflights",
    "airlines": [
      "Qatar Airways"
    ],
    "stopsOut": 1,
    "stopsIn": null
  },
  {
    "date": "2026-07-02",
    "departDate": "2026-10-23",
    "returnDate": "2026-11-09",
    "price": 1188.0,
    "source": "googleflights",
    "airlines": [
      "Qatar Airways"
    ],
    "stopsOut": 1,
    "stopsIn": null
  },
  {
    "date": "2026-07-02",
    "departDate": "2026-10-23",
    "returnDate": "2026-11-09",
    "price": 1245.0,
    "source": "googleflights",
    "airlines": [
      "THAI"
    ],
    "stopsOut": 1,
    "stopsIn": null
  },
  {
    "date": "2026-07-02",
    "departDate": "2026-10-02",
    "returnDate": "2026-10-19",
    "price": 1479.0,
    "source": "googleflights",
    "airlines": [
      "Gulf Air, Philippine Airlines"
    ],
    "stopsOut": 2,
    "stopsIn": null
  },
  {
    "date": "2026-07-02",
    "departDate": "2026-10-02",
    "returnDate": "2026-10-19",
    "price": 1486.0,
    "source": "googleflights",
    "airlines": [
      "Gulf Air, Philippine Airlines"
    ],
    "stopsOut": 2,
    "stopsIn": null
  },
  {
    "date": "2026-07-02",
    "departDate": "2026-10-02",
    "returnDate": "2026-10-19",
    "price": 1493.0,
    "source": "googleflights",
    "airlines": [
      "Air France"
    ],
    "stopsOut": 1,
    "stopsIn": null
  },
  {
    "date": "2026-07-02",
    "departDate": "2026-10-02",
    "returnDate": "2026-10-19",
    "price": 1533.0,
    "source": "googleflights",
    "airlines": [
      "Emirates"
    ],
    "stopsOut": 1,
    "stopsIn": null
  }
]
