{
  "airportPriority": {
    "europe": [
      {
        "code": "FCO",
        "dealRatePct": 16.7,
        "medianEur": 1042.0,
        "observations": 6
      },
      {
        "code": "FRA",
        "dealRatePct": 11.3,
        "medianEur": 1116.5,
        "observations": 222
      },
      {
        "code": "MUC",
        "dealRatePct": 10.2,
        "medianEur": 1130.0,
        "observations": 235
      },
      {
        "code": "PRG",
        "dealRatePct": 5.9,
        "medianEur": 1180.0,
        "observations": 17
      },
      {
        "code": "VIE",
        "dealRatePct": 3.6,
        "medianEur": 1064.0,
        "observations": 56
      },
      {
        "code": "MXP",
        "dealRatePct": 0.0,
        "medianEur": 909.0,
        "observations": 13
      },
      {
        "code": "AMS",
        "dealRatePct": 0.0,
        "medianEur": 1081.0,
        "observations": 17
      },
      {
        "code": "BUD",
        "dealRatePct": 0.0,
        "medianEur": 1156.0,
        "observations": 13
      },
      {
        "code": "FMM",
        "dealRatePct": 0.0,
        "medianEur": 1253.0,
        "observations": 1
      },
      {
        "code": "NUE",
        "dealRatePct": 0.0,
        "medianEur": 1335.5,
        "observations": 8
      }
    ],
    "japan": [
      {
        "code": "HND",
        "dealRatePct": 32.2,
        "medianEur": 1093.0,
        "observations": 171
      },
      {
        "code": "NRT",
        "dealRatePct": 27.4,
        "medianEur": 1068.5,
        "observations": 164
      },
      {
        "code": "KIX",
        "dealRatePct": 19.2,
        "medianEur": 1130.0,
        "observations": 177
      },
      {
        "code": "NGO",
        "dealRatePct": 3.6,
        "medianEur": 1290.0,
        "observations": 84
      },
      {
        "code": "ITM",
        "dealRatePct": 0.0,
        "medianEur": 1331.0,
        "observations": 11
      }
    ]
  },
  "cheapestDepartureDow": [
    {
      "dow": "ST",
      "dealRatePct": 15.3,
      "medianEur": 1148.0
    },
    {
      "dow": "PO",
      "dealRatePct": 8.6,
      "medianEur": 1047.0
    },
    {
      "dow": "PÁ",
      "dealRatePct": 8.4,
      "medianEur": 1080.0
    },
    {
      "dow": "ÚT",
      "dealRatePct": 7.9,
      "medianEur": 995.5
    },
    {
      "dow": "SO",
      "dealRatePct": 3.8,
      "medianEur": 1196.5
    },
    {
      "dow": "ČT",
      "dealRatePct": 0.0,
      "medianEur": 1197.0
    },
    {
      "dow": "NE",
      "dealRatePct": 0.0,
      "medianEur": 1206.0
    }
  ],
  "cheapestArrivalDow": [
    {
      "dow": "ST",
      "dealRatePct": 20.3,
      "medianEur": 1133.0
    },
    {
      "dow": "PO",
      "dealRatePct": 9.6,
      "medianEur": 1079.5
    },
    {
      "dow": "ÚT",
      "dealRatePct": 6.7,
      "medianEur": 1070.0
    },
    {
      "dow": "SO",
      "dealRatePct": 2.7,
      "medianEur": 1173.0
    },
    {
      "dow": "NE",
      "dealRatePct": 1.5,
      "medianEur": 1150.0
    },
    {
      "dow": "PÁ",
      "dealRatePct": 0.0,
      "medianEur": 1225.5
    },
    {
      "dow": "ČT",
      "dealRatePct": 0.0,
      "medianEur": 1327.5
    }
  ]
}
