[
  {
    "routeKey": "FRA-HND-roundtrip",
    "type": "roundtrip",
    "origin": "FRA",
    "destination": "HND",
    "returnOrigin": null,
    "returnDestination": null,
    "price": 863.0,
    "source": "googleflights",
    "departDate": "2026-10-28",
    "returnDate": "2026-11-18",
    "nights": 21,
    "airlines": [
      "Qatar Airways"
    ],
    "dealUrl": "https://www.google.com/travel/flights/search?tfs=GhoSCjIwMjYtMTAtMjhqBRIDRlJBcgUSA0hORBoaEgoyMDI2LTExLTE4agUSA0hORHIFEgNGUkFAAUgBmAEB&hl=en&curr=EUR",
    "observedDate": "2026-07-17",
    "segments": {
      "out": [],
      "in": []
    },
    "durationOutMin": null,
    "durationInMin": null,
    "stopsOut": 1,
    "stopsIn": null,
    "scannedPrice": null,
    "alternatives": [
      {
        "price": 866.0,
        "airlines": [
          "Qatar Airways"
        ],
        "source": "googleflights",
        "dealUrl": "https://www.google.com/travel/flights/search?tfs=GhoSCjIwMjYtMTAtMjhqBRIDRlJBcgUSA0hORBoaEgoyMDI2LTExLTE4agUSA0hORHIFEgNGUkFAAUgBmAEB&hl=en&curr=EUR",
        "stopsOut": 1,
        "stopsIn": null
      },
      {
        "price": 1019.0,
        "airlines": [
          "British Airways, Cathay Pacific"
        ],
        "source": "googleflights",
        "dealUrl": "https://www.google.com/travel/flights/search?tfs=GhoSCjIwMjYtMTAtMjhqBRIDRlJBcgUSA0hORBoaEgoyMDI2LTExLTE4agUSA0hORHIFEgNGUkFAAUgBmAEB&hl=en&curr=EUR",
        "stopsOut": 2,
        "stopsIn": null
      },
      {
        "price": 1080.0,
        "airlines": [
          "Emirates"
        ],
        "source": "googleflights",
        "dealUrl": "https://www.google.com/travel/flights/search?tfs=GhoSCjIwMjYtMTAtMjhqBRIDRlJBcgUSA0hORBoaEgoyMDI2LTExLTE4agUSA0hORHIFEgNGUkFAAUgBmAEB&hl=en&curr=EUR",
        "stopsOut": 1,
        "stopsIn": null
      }
    ],
    "flags": {
      "isNewLow": false,
      "priceDeltaEur": -381.0,
      "pctChange7d": -0.1,
      "isBigDrop": true,
      "staleDays": null
    }
  },
  {
    "routeKey": "MUC-HND-roundtrip",
    "type": "roundtrip",
    "origin": "MUC",
    "destination": "HND",
    "returnOrigin": null,
    "returnDestination": null,
    "price": 874.0,
    "source": "googleflights",
    "departDate": "2026-10-28",
    "returnDate": "2026-11-18",
    "nights": 21,
    "airlines": [
      "Qatar Airways"
    ],
    "dealUrl": "https://www.google.com/travel/flights/search?tfs=GhoSCjIwMjYtMTAtMjhqBRIDTVVDcgUSA0hORBoaEgoyMDI2LTExLTE4agUSA0hORHIFEgNNVUNAAUgBmAEB&hl=en&curr=EUR",
    "observedDate": "2026-07-17",
    "segments": {
      "out": [],
      "in": []
    },
    "durationOutMin": null,
    "durationInMin": null,
    "stopsOut": 1,
    "stopsIn": null,
    "scannedPrice": null,
    "alternatives": [
      {
        "price": 876.0,
        "airlines": [
          "Qatar Airways"
        ],
        "source": "googleflights",
        "dealUrl": "https://www.google.com/travel/flights/search?tfs=GhoSCjIwMjYtMTAtMjhqBRIDTVVDcgUSA0hORBoaEgoyMDI2LTExLTE4agUSA0hORHIFEgNNVUNAAUgBmAEB&hl=en&curr=EUR",
        "stopsOut": 1,
        "stopsIn": null
      },
      {
        "price": 1087.0,
        "airlines": [
          "Emirates"
        ],
        "source": "googleflights",
        "dealUrl": "https://www.google.com/travel/flights/search?tfs=GhoSCjIwMjYtMTAtMjhqBRIDTVVDcgUSA0hORBoaEgoyMDI2LTExLTE4agUSA0hORHIFEgNNVUNAAUgBmAEB&hl=en&curr=EUR",
        "stopsOut": 1,
        "stopsIn": null
      },
      {
        "price": 1128.0,
        "airlines": [
          "Scandinavian Airlines"
        ],
        "source": "googleflights",
        "dealUrl": "https://www.google.com/travel/flights/search?tfs=GhoSCjIwMjYtMTAtMjhqBRIDTVVDcgUSA0hORBoaEgoyMDI2LTExLTE4agUSA0hORHIFEgNNVUNAAUgBmAEB&hl=en&curr=EUR",
        "stopsOut": 1,
        "stopsIn": null
      }
    ],
    "flags": {
      "isNewLow": false,
      "priceDeltaEur": -353.0,
      "pctChange7d": 0.0,
      "isBigDrop": true,
      "staleDays": null
    }
  },
  {
    "routeKey": "FRA-HND-roundtrip",
    "type": "roundtrip",
    "origin": "FRA",
    "destination": "HND",
    "returnOrigin": null,
    "returnDestination": null,
    "price": 893.0,
    "source": "googleflights",
    "departDate": "2026-11-13",
    "returnDate": "2026-11-30",
    "nights": 17,
    "airlines": [
      "Qatar Airways"
    ],
    "dealUrl": "https://www.google.com/travel/flights/search?tfs=GhoSCjIwMjYtMTEtMTNqBRIDRlJBcgUSA0hORBoaEgoyMDI2LTExLTMwagUSA0hORHIFEgNGUkFAAUgBmAEB&hl=en&curr=EUR",
    "observedDate": "2026-07-17",
    "segments": {
      "out": [],
      "in": []
    },
    "durationOutMin": null,
    "durationInMin": null,
    "stopsOut": 1,
    "stopsIn": null,
    "scannedPrice": null,
    "alternatives": [
      {
        "price": 893.0,
        "airlines": [
          "Qatar Airways, JAL"
        ],
        "source": "googleflights",
        "dealUrl": "https://www.google.com/travel/flights/search?tfs=GhoSCjIwMjYtMTEtMTNqBRIDRlJBcgUSA0hORBoaEgoyMDI2LTExLTMwagUSA0hORHIFEgNGUkFAAUgBmAEB&hl=en&curr=EUR",
        "stopsOut": 1,
        "stopsIn": null
      },
      {
        "price": 965.0,
        "airlines": [
          "Emirates"
        ],
        "source": "googleflights",
        "dealUrl": "https://www.google.com/travel/flights/search?tfs=GhoSCjIwMjYtMTEtMTNqBRIDRlJBcgUSA0hORBoaEgoyMDI2LTExLTMwagUSA0hORHIFEgNGUkFAAUgBmAEB&hl=en&curr=EUR",
        "stopsOut": 1,
        "stopsIn": null
      }
    ],
    "flags": {
      "isNewLow": false,
      "priceDeltaEur": -351.0,
      "pctChange7d": 3.4,
      "isBigDrop": true,
      "staleDays": null
    }
  },
  {
    "routeKey": "FRA-NRT-roundtrip",
    "type": "roundtrip",
    "origin": "FRA",
    "destination": "NRT",
    "returnOrigin": null,
    "returnDestination": null,
    "price": 899.0,
    "source": "googleflights",
    "departDate": "2026-11-13",
    "returnDate": "2026-11-30",
    "nights": 17,
    "airlines": [
      "Emirates"
    ],
    "dealUrl": "https://www.google.com/travel/flights/search?tfs=GhoSCjIwMjYtMTEtMTNqBRIDRlJBcgUSA05SVBoaEgoyMDI2LTExLTMwagUSA05SVHIFEgNGUkFAAUgBmAEB&hl=en&curr=EUR",
    "observedDate": "2026-07-17",
    "segments": {
      "out": [],
      "in": []
    },
    "durationOutMin": null,
    "durationInMin": null,
    "stopsOut": 1,
    "stopsIn": null,
    "scannedPrice": null,
    "alternatives": [
      {
        "price": 999.0,
        "airlines": [
          "China Airlines"
        ],
        "source": "googleflights",
        "dealUrl": "https://www.google.com/travel/flights/search?tfs=GhoSCjIwMjYtMTEtMTNqBRIDRlJBcgUSA05SVBoaEgoyMDI2LTExLTMwagUSA05SVHIFEgNGUkFAAUgBmAEB&hl=en&curr=EUR",
        "stopsOut": 1,
        "stopsIn": null
      }
    ],
    "flags": {
      "isNewLow": false,
      "priceDeltaEur": -247.0,
      "pctChange7d": 0.7,
      "isBigDrop": true,
      "staleDays": null
    }
  },
  {
    "routeKey": "MUC-HND-roundtrip",
    "type": "roundtrip",
    "origin": "MUC",
    "destination": "HND",
    "returnOrigin": null,
    "returnDestination": null,
    "price": 904.0,
    "source": "googleflights",
    "departDate": "2026-11-13",
    "returnDate": "2026-11-30",
    "nights": 17,
    "airlines": [
      "Qatar Airways"
    ],
    "dealUrl": "https://www.google.com/travel/flights/search?tfs=GhoSCjIwMjYtMTEtMTNqBRIDTVVDcgUSA0hORBoaEgoyMDI2LTExLTMwagUSA0hORHIFEgNNVUNAAUgBmAEB&hl=en&curr=EUR",
    "observedDate": "2026-07-17",
    "segments": {
      "out": [],
      "in": []
    },
    "durationOutMin": null,
    "durationInMin": null,
    "stopsOut": 1,
    "stopsIn": null,
    "scannedPrice": null,
    "alternatives": [
      {
        "price": 904.0,
        "airlines": [
          "Qatar Airways, JAL"
        ],
        "source": "googleflights",
        "dealUrl": "https://www.google.com/travel/flights/search?tfs=GhoSCjIwMjYtMTEtMTNqBRIDTVVDcgUSA0hORBoaEgoyMDI2LTExLTMwagUSA0hORHIFEgNNVUNAAUgBmAEB&hl=en&curr=EUR",
        "stopsOut": 1,
        "stopsIn": null
      },
      {
        "price": 906.0,
        "airlines": [
          "Qatar Airways"
        ],
        "source": "googleflights",
        "dealUrl": "https://www.google.com/travel/flights/search?tfs=GhoSCjIwMjYtMTEtMTNqBRIDTVVDcgUSA0hORBoaEgoyMDI2LTExLTMwagUSA0hORHIFEgNNVUNAAUgBmAEB&hl=en&curr=EUR",
        "stopsOut": 1,
        "stopsIn": null
      },
      {
        "price": 948.0,
        "airlines": [
          "Emirates"
        ],
        "source": "googleflights",
        "dealUrl": "https://www.google.com/travel/flights/search?tfs=GhoSCjIwMjYtMTEtMTNqBRIDTVVDcgUSA0hORBoaEgoyMDI2LTExLTMwagUSA0hORHIFEgNNVUNAAUgBmAEB&hl=en&curr=EUR",
        "stopsOut": 1,
        "stopsIn": null
      }
    ],
    "flags": {
      "isNewLow": false,
      "priceDeltaEur": -323.0,
      "pctChange7d": 3.4,
      "isBigDrop": true,
      "staleDays": null
    }
  },
  {
    "routeKey": "MUC-NRT-roundtrip",
    "type": "roundtrip",
    "origin": "MUC",
    "destination": "NRT",
    "returnOrigin": null,
    "returnDestination": null,
    "price": 961.0,
    "source": "googleflights",
    "departDate": "2026-11-13",
    "returnDate": "2026-11-30",
    "nights": 17,
    "airlines": [
      "Qatar Airways"
    ],
    "dealUrl": "https://www.google.com/travel/flights/search?tfs=GhoSCjIwMjYtMTEtMTNqBRIDTVVDcgUSA05SVBoaEgoyMDI2LTExLTMwagUSA05SVHIFEgNNVUNAAUgBmAEB&hl=en&curr=EUR",
    "observedDate": "2026-07-17",
    "segments": {
      "out": [],
      "in": []
    },
    "durationOutMin": null,
    "durationInMin": null,
    "stopsOut": 1,
    "stopsIn": null,
    "scannedPrice": null,
    "alternatives": [
      {
        "price": 1112.0,
        "airlines": [
          "Emirates"
        ],
        "source": "googleflights",
        "dealUrl": "https://www.google.com/travel/flights/search?tfs=GhoSCjIwMjYtMTEtMTNqBRIDTVVDcgUSA05SVBoaEgoyMDI2LTExLTMwagUSA05SVHIFEgNNVUNAAUgBmAEB&hl=en&curr=EUR",
        "stopsOut": 1,
        "stopsIn": null
      },
      {
        "price": 1126.0,
        "airlines": [
          "Qatar Airways"
        ],
        "source": "googleflights",
        "dealUrl": "https://www.google.com/travel/flights/search?tfs=GhoSCjIwMjYtMTEtMTNqBRIDTVVDcgUSA05SVBoaEgoyMDI2LTExLTMwagUSA05SVHIFEgNNVUNAAUgBmAEB&hl=en&curr=EUR",
        "stopsOut": 1,
        "stopsIn": null
      },
      {
        "price": 1164.0,
        "airlines": [
          "Lufthansa, Cathay Pacific"
        ],
        "source": "googleflights",
        "dealUrl": "https://www.google.com/travel/flights/search?tfs=GhoSCjIwMjYtMTEtMTNqBRIDTVVDcgUSA05SVBoaEgoyMDI2LTExLTMwagUSA05SVHIFEgNNVUNAAUgBmAEB&hl=en&curr=EUR",
        "stopsOut": 2,
        "stopsIn": null
      }
    ],
    "flags": {
      "isNewLow": false,
      "priceDeltaEur": -277.0,
      "pctChange7d": 9.8,
      "isBigDrop": true,
      "staleDays": null
    }
  },
  {
    "routeKey": "MUC-KIX-roundtrip",
    "type": "roundtrip",
    "origin": "MUC",
    "destination": "KIX",
    "returnOrigin": null,
    "returnDestination": null,
    "price": 981.0,
    "source": "googleflights",
    "departDate": "2026-11-13",
    "returnDate": "2026-11-30",
    "nights": 17,
    "airlines": [
      "Emirates"
    ],
    "dealUrl": "https://www.google.com/travel/flights/search?tfs=GhoSCjIwMjYtMTEtMTNqBRIDTVVDcgUSA0tJWBoaEgoyMDI2LTExLTMwagUSA0tJWHIFEgNNVUNAAUgBmAEB&hl=en&curr=EUR",
    "observedDate": "2026-07-17",
    "segments": {
      "out": [],
      "in": []
    },
    "durationOutMin": null,
    "durationInMin": null,
    "stopsOut": 1,
    "stopsIn": null,
    "scannedPrice": null,
    "alternatives": [
      {
        "price": 1015.0,
        "airlines": [
          "Emirates"
        ],
        "source": "googleflights",
        "dealUrl": "https://www.google.com/travel/flights/search?tfs=GhoSCjIwMjYtMTEtMTNqBRIDTVVDcgUSA0tJWBoaEgoyMDI2LTExLTMwagUSA0tJWHIFEgNNVUNAAUgBmAEB&hl=en&curr=EUR",
        "stopsOut": 1,
        "stopsIn": null
      },
      {
        "price": 1073.0,
        "airlines": [
          "Emirates, Jetstar"
        ],
        "source": "googleflights",
        "dealUrl": "https://www.google.com/travel/flights/search?tfs=GhoSCjIwMjYtMTEtMTNqBRIDTVVDcgUSA0tJWBoaEgoyMDI2LTExLTMwagUSA0tJWHIFEgNNVUNAAUgBmAEB&hl=en&curr=EUR",
        "stopsOut": 2,
        "stopsIn": null
      },
      {
        "price": 1116.0,
        "airlines": [
          "Emirates, ANA"
        ],
        "source": "googleflights",
        "dealUrl": "https://www.google.com/travel/flights/search?tfs=GhoSCjIwMjYtMTEtMTNqBRIDTVVDcgUSA0tJWBoaEgoyMDI2LTExLTMwagUSA0tJWHIFEgNNVUNAAUgBmAEB&hl=en&curr=EUR",
        "stopsOut": 2,
        "stopsIn": null
      },
      {
        "price": 1166.0,
        "airlines": [
          "Lufthansa, Cathay Pacific"
        ],
        "source": "googleflights",
        "dealUrl": "https://www.google.com/travel/flights/search?tfs=GhoSCjIwMjYtMTEtMTNqBRIDTVVDcgUSA0tJWBoaEgoyMDI2LTExLTMwagUSA0tJWHIFEgNNVUNAAUgBmAEB&hl=en&curr=EUR",
        "stopsOut": 2,
        "stopsIn": null
      }
    ],
    "flags": {
      "isNewLow": false,
      "priceDeltaEur": -240.0,
      "pctChange7d": -16.2,
      "isBigDrop": true,
      "staleDays": null
    }
  },
  {
    "routeKey": "FRA-NGO-roundtrip",
    "type": "roundtrip",
    "origin": "FRA",
    "destination": "NGO",
    "returnOrigin": null,
    "returnDestination": null,
    "price": 983.0,
    "source": "googleflights",
    "departDate": "2026-11-13",
    "returnDate": "2026-11-30",
    "nights": 17,
    "airlines": [
      "Qatar Airways, JAL"
    ],
    "dealUrl": "https://www.google.com/travel/flights/search?tfs=GhoSCjIwMjYtMTEtMTNqBRIDRlJBcgUSA05HTxoaEgoyMDI2LTExLTMwagUSA05HT3IFEgNGUkFAAUgBmAEB&hl=en&curr=EUR",
    "observedDate": "2026-07-17",
    "segments": {
      "out": [],
      "in": []
    },
    "durationOutMin": null,
    "durationInMin": null,
    "stopsOut": 2,
    "stopsIn": null,
    "scannedPrice": null,
    "alternatives": [
      {
        "price": 1011.0,
        "airlines": [
          "Cathay Pacific"
        ],
        "source": "googleflights",
        "dealUrl": "https://www.google.com/travel/flights/search?tfs=GhoSCjIwMjYtMTEtMTNqBRIDRlJBcgUSA05HTxoaEgoyMDI2LTExLTMwagUSA05HT3IFEgNGUkFAAUgBmAEB&hl=en&curr=EUR",
        "stopsOut": 1,
        "stopsIn": null
      },
      {
        "price": 1018.0,
        "airlines": [
          "Cathay Pacific"
        ],
        "source": "googleflights",
        "dealUrl": "https://www.google.com/travel/flights/search?tfs=GhoSCjIwMjYtMTEtMTNqBRIDRlJBcgUSA05HTxoaEgoyMDI2LTExLTMwagUSA05HT3IFEgNGUkFAAUgBmAEB&hl=en&curr=EUR",
        "stopsOut": 2,
        "stopsIn": null
      },
      {
        "price": 1023.0,
        "airlines": [
          "Qatar Airways, JAL"
        ],
        "source": "googleflights",
        "dealUrl": "https://www.google.com/travel/flights/search?tfs=GhoSCjIwMjYtMTEtMTNqBRIDRlJBcgUSA05HTxoaEgoyMDI2LTExLTMwagUSA05HT3IFEgNGUkFAAUgBmAEB&hl=en&curr=EUR",
        "stopsOut": 2,
        "stopsIn": null
      }
    ],
    "flags": {
      "isNewLow": false,
      "priceDeltaEur": -687.0,
      "pctChange7d": -21.5,
      "isBigDrop": true,
      "staleDays": null
    }
  },
  {
    "routeKey": "FRA-KIX-roundtrip",
    "type": "roundtrip",
    "origin": "FRA",
    "destination": "KIX",
    "returnOrigin": null,
    "returnDestination": null,
    "price": 1002.0,
    "source": "googleflights",
    "departDate": "2026-11-13",
    "returnDate": "2026-11-30",
    "nights": 17,
    "airlines": [
      "China Airlines"
    ],
    "dealUrl": "https://www.google.com/travel/flights/search?tfs=GhoSCjIwMjYtMTEtMTNqBRIDRlJBcgUSA0tJWBoaEgoyMDI2LTExLTMwagUSA0tJWHIFEgNGUkFAAUgBmAEB&hl=en&curr=EUR",
    "observedDate": "2026-07-17",
    "segments": {
      "out": [],
      "in": []
    },
    "durationOutMin": null,
    "durationInMin": null,
    "stopsOut": 1,
    "stopsIn": null,
    "scannedPrice": null,
    "alternatives": [
      {
        "price": 1018.0,
        "airlines": [
          "Emirates"
        ],
        "source": "googleflights",
        "dealUrl": "https://www.google.com/travel/flights/search?tfs=GhoSCjIwMjYtMTEtMTNqBRIDRlJBcgUSA0tJWBoaEgoyMDI2LTExLTMwagUSA0tJWHIFEgNGUkFAAUgBmAEB&hl=en&curr=EUR",
        "stopsOut": 1,
        "stopsIn": null
      },
      {
        "price": 1044.0,
        "airlines": [
          "Finnair"
        ],
        "source": "googleflights",
        "dealUrl": "https://www.google.com/travel/flights/search?tfs=GhoSCjIwMjYtMTEtMTNqBRIDRlJBcgUSA0tJWBoaEgoyMDI2LTExLTMwagUSA0tJWHIFEgNGUkFAAUgBmAEB&hl=en&curr=EUR",
        "stopsOut": 1,
        "stopsIn": null
      },
      {
        "price": 1133.0,
        "airlines": [
          "Cathay Pacific"
        ],
        "source": "googleflights",
        "dealUrl": "https://www.google.com/travel/flights/search?tfs=GhoSCjIwMjYtMTEtMTNqBRIDRlJBcgUSA0tJWBoaEgoyMDI2LTExLTMwagUSA0tJWHIFEgNGUkFAAUgBmAEB&hl=en&curr=EUR",
        "stopsOut": 1,
        "stopsIn": null
      }
    ],
    "flags": {
      "isNewLow": false,
      "priceDeltaEur": -101.0,
      "pctChange7d": 0.0,
      "isBigDrop": false,
      "staleDays": null
    }
  },
  {
    "routeKey": "FRA-NRT-roundtrip",
    "type": "roundtrip",
    "origin": "FRA",
    "destination": "NRT",
    "returnOrigin": null,
    "returnDestination": null,
    "price": 1057.0,
    "source": "googleflights",
    "departDate": "2026-10-28",
    "returnDate": "2026-11-18",
    "nights": 21,
    "airlines": [
      "Emirates"
    ],
    "dealUrl": "https://www.google.com/travel/flights/search?tfs=GhoSCjIwMjYtMTAtMjhqBRIDRlJBcgUSA05SVBoaEgoyMDI2LTExLTE4agUSA05SVHIFEgNGUkFAAUgBmAEB&hl=en&curr=EUR",
    "observedDate": "2026-07-17",
    "segments": {
      "out": [],
      "in": []
    },
    "durationOutMin": null,
    "durationInMin": null,
    "stopsOut": 1,
    "stopsIn": null,
    "scannedPrice": null,
    "alternatives": [
      {
        "price": 1105.0,
        "airlines": [
          "Qatar Airways"
        ],
        "source": "googleflights",
        "dealUrl": "https://www.google.com/travel/flights/search?tfs=GhoSCjIwMjYtMTAtMjhqBRIDRlJBcgUSA05SVBoaEgoyMDI2LTExLTE4agUSA05SVHIFEgNGUkFAAUgBmAEB&hl=en&curr=EUR",
        "stopsOut": 1,
        "stopsIn": null
      },
      {
        "price": 1200.0,
        "airlines": [
          "Qatar Airways"
        ],
        "source": "googleflights",
        "dealUrl": "https://www.google.com/travel/flights/search?tfs=GhoSCjIwMjYtMTAtMjhqBRIDRlJBcgUSA05SVBoaEgoyMDI2LTExLTE4agUSA05SVHIFEgNGUkFAAUgBmAEB&hl=en&curr=EUR",
        "stopsOut": 1,
        "stopsIn": null
      }
    ],
    "flags": {
      "isNewLow": false,
      "priceDeltaEur": -89.0,
      "pctChange7d": 18.4,
      "isBigDrop": false,
      "staleDays": null
    }
  },
  {
    "routeKey": "FRA-KIX-roundtrip",
    "type": "roundtrip",
    "origin": "FRA",
    "destination": "KIX",
    "returnOrigin": null,
    "returnDestination": null,
    "price": 1061.0,
    "source": "googleflights",
    "departDate": "2026-10-28",
    "returnDate": "2026-11-18",
    "nights": 21,
    "airlines": [
      "KLM"
    ],
    "dealUrl": "https://www.google.com/travel/flights/search?tfs=GhoSCjIwMjYtMTAtMjhqBRIDRlJBcgUSA0tJWBoaEgoyMDI2LTExLTE4agUSA0tJWHIFEgNGUkFAAUgBmAEB&hl=en&curr=EUR",
    "observedDate": "2026-07-17",
    "segments": {
      "out": [],
      "in": []
    },
    "durationOutMin": null,
    "durationInMin": null,
    "stopsOut": 1,
    "stopsIn": null,
    "scannedPrice": null,
    "alternatives": [
      {
        "price": 1104.0,
        "airlines": [
          "Finnair"
        ],
        "source": "googleflights",
        "dealUrl": "https://www.google.com/travel/flights/search?tfs=GhoSCjIwMjYtMTAtMjhqBRIDRlJBcgUSA0tJWBoaEgoyMDI2LTExLTE4agUSA0tJWHIFEgNGUkFAAUgBmAEB&hl=en&curr=EUR",
        "stopsOut": 1,
        "stopsIn": null
      },
      {
        "price": 1132.0,
        "airlines": [
          "Korean Air"
        ],
        "source": "googleflights",
        "dealUrl": "https://www.google.com/travel/flights/search?tfs=GhoSCjIwMjYtMTAtMjhqBRIDRlJBcgUSA0tJWBoaEgoyMDI2LTExLTE4agUSA0tJWHIFEgNGUkFAAUgBmAEB&hl=en&curr=EUR",
        "stopsOut": 1,
        "stopsIn": null
      }
    ],
    "flags": {
      "isNewLow": false,
      "priceDeltaEur": -42.0,
      "pctChange7d": 5.9,
      "isBigDrop": false,
      "staleDays": null
    }
  },
  {
    "routeKey": "MUC-NRT-roundtrip",
    "type": "roundtrip",
    "origin": "MUC",
    "destination": "NRT",
    "returnOrigin": null,
    "returnDestination": null,
    "price": 1064.0,
    "source": "googleflights",
    "departDate": "2026-10-28",
    "returnDate": "2026-11-18",
    "nights": 21,
    "airlines": [
      "Emirates"
    ],
    "dealUrl": "https://www.google.com/travel/flights/search?tfs=GhoSCjIwMjYtMTAtMjhqBRIDTVVDcgUSA05SVBoaEgoyMDI2LTExLTE4agUSA05SVHIFEgNNVUNAAUgBmAEB&hl=en&curr=EUR",
    "observedDate": "2026-07-17",
    "segments": {
      "out": [],
      "in": []
    },
    "durationOutMin": null,
    "durationInMin": null,
    "stopsOut": 1,
    "stopsIn": null,
    "scannedPrice": null,
    "alternatives": [
      {
        "price": 1094.0,
        "airlines": [
          "Qatar Airways"
        ],
        "source": "googleflights",
        "dealUrl": "https://www.google.com/travel/flights/search?tfs=GhoSCjIwMjYtMTAtMjhqBRIDTVVDcgUSA05SVBoaEgoyMDI2LTExLTE4agUSA05SVHIFEgNNVUNAAUgBmAEB&hl=en&curr=EUR",
        "stopsOut": 1,
        "stopsIn": null
      },
      {
        "price": 1176.0,
        "airlines": [
          "Emirates"
        ],
        "source": "googleflights",
        "dealUrl": "https://www.google.com/travel/flights/search?tfs=GhoSCjIwMjYtMTAtMjhqBRIDTVVDcgUSA05SVBoaEgoyMDI2LTExLTE4agUSA05SVHIFEgNNVUNAAUgBmAEB&hl=en&curr=EUR",
        "stopsOut": 1,
        "stopsIn": null
      },
      {
        "price": 1188.0,
        "airlines": [
          "Qatar Airways"
        ],
        "source": "googleflights",
        "dealUrl": "https://www.google.com/travel/flights/search?tfs=GhoSCjIwMjYtMTAtMjhqBRIDTVVDcgUSA05SVBoaEgoyMDI2LTExLTE4agUSA05SVHIFEgNNVUNAAUgBmAEB&hl=en&curr=EUR",
        "stopsOut": 1,
        "stopsIn": null
      }
    ],
    "flags": {
      "isNewLow": false,
      "priceDeltaEur": -174.0,
      "pctChange7d": 21.6,
      "isBigDrop": false,
      "staleDays": null
    }
  },
  {
    "routeKey": "MUC-KIX-roundtrip",
    "type": "roundtrip",
    "origin": "MUC",
    "destination": "KIX",
    "returnOrigin": null,
    "returnDestination": null,
    "price": 1089.0,
    "source": "googleflights",
    "departDate": "2026-10-28",
    "returnDate": "2026-11-18",
    "nights": 21,
    "airlines": [
      "KLM"
    ],
    "dealUrl": "https://www.google.com/travel/flights/search?tfs=GhoSCjIwMjYtMTAtMjhqBRIDTVVDcgUSA0tJWBoaEgoyMDI2LTExLTE4agUSA0tJWHIFEgNNVUNAAUgBmAEB&hl=en&curr=EUR",
    "observedDate": "2026-07-17",
    "segments": {
      "out": [],
      "in": []
    },
    "durationOutMin": null,
    "durationInMin": null,
    "stopsOut": 1,
    "stopsIn": null,
    "scannedPrice": null,
    "alternatives": [
      {
        "price": 1123.0,
        "airlines": [
          "KLM"
        ],
        "source": "googleflights",
        "dealUrl": "https://www.google.com/travel/flights/search?tfs=GhoSCjIwMjYtMTAtMjhqBRIDTVVDcgUSA0tJWBoaEgoyMDI2LTExLTE4agUSA0tJWHIFEgNNVUNAAUgBmAEB&hl=en&curr=EUR",
        "stopsOut": 1,
        "stopsIn": null
      },
      {
        "price": 1177.0,
        "airlines": [
          "Air France, KLM"
        ],
        "source": "googleflights",
        "dealUrl": "https://www.google.com/travel/flights/search?tfs=GhoSCjIwMjYtMTAtMjhqBRIDTVVDcgUSA0tJWBoaEgoyMDI2LTExLTE4agUSA0tJWHIFEgNNVUNAAUgBmAEB&hl=en&curr=EUR",
        "stopsOut": 2,
        "stopsIn": null
      },
      {
        "price": 1230.0,
        "airlines": [
          "THAI"
        ],
        "source": "googleflights",
        "dealUrl": "https://www.google.com/travel/flights/search?tfs=GhoSCjIwMjYtMTAtMjhqBRIDTVVDcgUSA0tJWBoaEgoyMDI2LTExLTE4agUSA0tJWHIFEgNNVUNAAUgBmAEB&hl=en&curr=EUR",
        "stopsOut": 1,
        "stopsIn": null
      }
    ],
    "flags": {
      "isNewLow": false,
      "priceDeltaEur": -132.0,
      "pctChange7d": -6.9,
      "isBigDrop": false,
      "staleDays": null
    }
  },
  {
    "routeKey": "FRA-KIX-roundtrip",
    "type": "roundtrip",
    "origin": "FRA",
    "destination": "KIX",
    "returnOrigin": null,
    "returnDestination": null,
    "price": 1102.0,
    "source": "googleflights",
    "departDate": "2026-10-07",
    "returnDate": "2026-10-28",
    "nights": 21,
    "airlines": [
      "Cathay Pacific"
    ],
    "dealUrl": "https://www.google.com/travel/flights/search?tfs=GhoSCjIwMjYtMTAtMDdqBRIDRlJBcgUSA0tJWBoaEgoyMDI2LTEwLTI4agUSA0tJWHIFEgNGUkFAAUgBmAEB&hl=en&curr=EUR",
    "observedDate": "2026-07-17",
    "segments": {
      "out": [],
      "in": []
    },
    "durationOutMin": null,
    "durationInMin": null,
    "stopsOut": 1,
    "stopsIn": null,
    "scannedPrice": null,
    "alternatives": [
      {
        "price": 1294.0,
        "airlines": [
          "China Airlines"
        ],
        "source": "googleflights",
        "dealUrl": "https://www.google.com/travel/flights/search?tfs=GhoSCjIwMjYtMTAtMDdqBRIDRlJBcgUSA0tJWBoaEgoyMDI2LTEwLTI4agUSA0tJWHIFEgNGUkFAAUgBmAEB&hl=en&curr=EUR",
        "stopsOut": 1,
        "stopsIn": null
      },
      {
        "price": 1319.0,
        "airlines": [
          "Cathay Pacific"
        ],
        "source": "googleflights",
        "dealUrl": "https://www.google.com/travel/flights/search?tfs=GhoSCjIwMjYtMTAtMDdqBRIDRlJBcgUSA0tJWBoaEgoyMDI2LTEwLTI4agUSA0tJWHIFEgNGUkFAAUgBmAEB&hl=en&curr=EUR",
        "stopsOut": 1,
        "stopsIn": null
      },
      {
        "price": 1335.0,
        "airlines": [
          "THAI"
        ],
        "source": "googleflights",
        "dealUrl": "https://www.google.com/travel/flights/search?tfs=GhoSCjIwMjYtMTAtMDdqBRIDRlJBcgUSA0tJWBoaEgoyMDI2LTEwLTI4agUSA0tJWHIFEgNGUkFAAUgBmAEB&hl=en&curr=EUR",
        "stopsOut": 1,
        "stopsIn": null
      }
    ],
    "flags": {
      "isNewLow": false,
      "priceDeltaEur": -1.0,
      "pctChange7d": 10.0,
      "isBigDrop": false,
      "staleDays": null
    }
  },
  {
    "routeKey": "FRA-NRT-roundtrip",
    "type": "roundtrip",
    "origin": "FRA",
    "destination": "NRT",
    "returnOrigin": null,
    "returnDestination": null,
    "price": 1167.0,
    "source": "googleflights",
    "departDate": "2026-10-07",
    "returnDate": "2026-10-28",
    "nights": 21,
    "airlines": [
      "THAI"
    ],
    "dealUrl": "https://www.google.com/travel/flights/search?tfs=GhoSCjIwMjYtMTAtMDdqBRIDRlJBcgUSA05SVBoaEgoyMDI2LTEwLTI4agUSA05SVHIFEgNGUkFAAUgBmAEB&hl=en&curr=EUR",
    "observedDate": "2026-07-17",
    "segments": {
      "out": [],
      "in": []
    },
    "durationOutMin": null,
    "durationInMin": null,
    "stopsOut": 1,
    "stopsIn": null,
    "scannedPrice": null,
    "alternatives": [
      {
        "price": 1273.0,
        "airlines": [
          "THAI"
        ],
        "source": "googleflights",
        "dealUrl": "https://www.google.com/travel/flights/search?tfs=GhoSCjIwMjYtMTAtMDdqBRIDRlJBcgUSA05SVBoaEgoyMDI2LTEwLTI4agUSA05SVHIFEgNGUkFAAUgBmAEB&hl=en&curr=EUR",
        "stopsOut": 1,
        "stopsIn": null
      }
    ],
    "flags": {
      "isNewLow": false,
      "priceDeltaEur": 21.0,
      "pctChange7d": 30.7,
      "isBigDrop": false,
      "staleDays": null
    }
  },
  {
    "routeKey": "MUC-NRT-roundtrip",
    "type": "roundtrip",
    "origin": "MUC",
    "destination": "NRT",
    "returnOrigin": null,
    "returnDestination": null,
    "price": 1203.0,
    "source": "googleflights",
    "departDate": "2026-10-07",
    "returnDate": "2026-10-28",
    "nights": 21,
    "airlines": [
      "Emirates, Jetstar"
    ],
    "dealUrl": "https://www.google.com/travel/flights/search?tfs=GhoSCjIwMjYtMTAtMDdqBRIDTVVDcgUSA05SVBoaEgoyMDI2LTEwLTI4agUSA05SVHIFEgNNVUNAAUgBmAEB&hl=en&curr=EUR",
    "observedDate": "2026-07-17",
    "segments": {
      "out": [],
      "in": []
    },
    "durationOutMin": null,
    "durationInMin": null,
    "stopsOut": 2,
    "stopsIn": null,
    "scannedPrice": null,
    "alternatives": [
      {
        "price": 1226.0,
        "airlines": [
          "THAI"
        ],
        "source": "googleflights",
        "dealUrl": "https://www.google.com/travel/flights/search?tfs=GhoSCjIwMjYtMTAtMDdqBRIDTVVDcgUSA05SVBoaEgoyMDI2LTEwLTI4agUSA05SVHIFEgNNVUNAAUgBmAEB&hl=en&curr=EUR",
        "stopsOut": 1,
        "stopsIn": null
      },
      {
        "price": 1228.0,
        "airlines": [
          "LOT"
        ],
        "source": "googleflights",
        "dealUrl": "https://www.google.com/travel/flights/search?tfs=GhoSCjIwMjYtMTAtMDdqBRIDTVVDcgUSA05SVBoaEgoyMDI2LTEwLTI4agUSA05SVHIFEgNNVUNAAUgBmAEB&hl=en&curr=EUR",
        "stopsOut": 1,
        "stopsIn": null
      }
    ],
    "flags": {
      "isNewLow": false,
      "priceDeltaEur": -35.0,
      "pctChange7d": 37.5,
      "isBigDrop": false,
      "staleDays": null
    }
  },
  {
    "routeKey": "MUC-HND-roundtrip",
    "type": "roundtrip",
    "origin": "MUC",
    "destination": "HND",
    "returnOrigin": null,
    "returnDestination": null,
    "price": 1226.0,
    "source": "googleflights",
    "departDate": "2026-10-07",
    "returnDate": "2026-10-28",
    "nights": 21,
    "airlines": [
      "THAI"
    ],
    "dealUrl": "https://www.google.com/travel/flights/search?tfs=GhoSCjIwMjYtMTAtMDdqBRIDTVVDcgUSA0hORBoaEgoyMDI2LTEwLTI4agUSA0hORHIFEgNNVUNAAUgBmAEB&hl=en&curr=EUR",
    "observedDate": "2026-07-17",
    "segments": {
      "out": [],
      "in": []
    },
    "durationOutMin": null,
    "durationInMin": null,
    "stopsOut": 1,
    "stopsIn": null,
    "scannedPrice": null,
    "alternatives": [
      {
        "price": 1279.0,
        "airlines": [
          "Gulf Air, Philippine Airlines"
        ],
        "source": "googleflights",
        "dealUrl": "https://www.google.com/travel/flights/search?tfs=GhoSCjIwMjYtMTAtMDdqBRIDTVVDcgUSA0hORBoaEgoyMDI2LTEwLTI4agUSA0hORHIFEgNNVUNAAUgBmAEB&hl=en&curr=EUR",
        "stopsOut": 2,
        "stopsIn": null
      },
      {
        "price": 1333.0,
        "airlines": [
          "Turkish Airlines, ANA"
        ],
        "source": "googleflights",
        "dealUrl": "https://www.google.com/travel/flights/search?tfs=GhoSCjIwMjYtMTAtMDdqBRIDTVVDcgUSA0hORBoaEgoyMDI2LTEwLTI4agUSA0hORHIFEgNNVUNAAUgBmAEB&hl=en&curr=EUR",
        "stopsOut": 1,
        "stopsIn": null
      },
      {
        "price": 1401.0,
        "airlines": [
          "THAI"
        ],
        "source": "googleflights",
        "dealUrl": "https://www.google.com/travel/flights/search?tfs=GhoSCjIwMjYtMTAtMDdqBRIDTVVDcgUSA0hORBoaEgoyMDI2LTEwLTI4agUSA0hORHIFEgNNVUNAAUgBmAEB&hl=en&curr=EUR",
        "stopsOut": 1,
        "stopsIn": null
      }
    ],
    "flags": {
      "isNewLow": false,
      "priceDeltaEur": -1.0,
      "pctChange7d": 40.3,
      "isBigDrop": false,
      "staleDays": null
    }
  },
  {
    "routeKey": "FRA-HND-roundtrip",
    "type": "roundtrip",
    "origin": "FRA",
    "destination": "HND",
    "returnOrigin": null,
    "returnDestination": null,
    "price": 1243.0,
    "source": "googleflights",
    "departDate": "2026-10-07",
    "returnDate": "2026-10-28",
    "nights": 21,
    "airlines": [
      "THAI"
    ],
    "dealUrl": "https://www.google.com/travel/flights/search?tfs=GhoSCjIwMjYtMTAtMDdqBRIDRlJBcgUSA0hORBoaEgoyMDI2LTEwLTI4agUSA0hORHIFEgNGUkFAAUgBmAEB&hl=en&curr=EUR",
    "observedDate": "2026-07-17",
    "segments": {
      "out": [],
      "in": []
    },
    "durationOutMin": null,
    "durationInMin": null,
    "stopsOut": 1,
    "stopsIn": null,
    "scannedPrice": null,
    "alternatives": [
      {
        "price": 1378.0,
        "airlines": [
          "Turkish Airlines, ANA"
        ],
        "source": "googleflights",
        "dealUrl": "https://www.google.com/travel/flights/search?tfs=GhoSCjIwMjYtMTAtMDdqBRIDRlJBcgUSA0hORBoaEgoyMDI2LTEwLTI4agUSA0hORHIFEgNGUkFAAUgBmAEB&hl=en&curr=EUR",
        "stopsOut": 1,
        "stopsIn": null
      },
      {
        "price": 1381.0,
        "airlines": [
          "Turkish Airlines, ANA"
        ],
        "source": "googleflights",
        "dealUrl": "https://www.google.com/travel/flights/search?tfs=GhoSCjIwMjYtMTAtMDdqBRIDRlJBcgUSA0hORBoaEgoyMDI2LTEwLTI4agUSA0hORHIFEgNGUkFAAUgBmAEB&hl=en&curr=EUR",
        "stopsOut": 1,
        "stopsIn": null
      },
      {
        "price": 1517.0,
        "airlines": [
          "China Airlines"
        ],
        "source": "googleflights",
        "dealUrl": "https://www.google.com/travel/flights/search?tfs=GhoSCjIwMjYtMTAtMDdqBRIDRlJBcgUSA0hORBoaEgoyMDI2LTEwLTI4agUSA0hORHIFEgNGUkFAAUgBmAEB&hl=en&curr=EUR",
        "stopsOut": 1,
        "stopsIn": null
      },
      {
        "price": 1542.0,
        "airlines": [
          "Scandinavian Airlines"
        ],
        "source": "googleflights",
        "dealUrl": "https://www.google.com/travel/flights/search?tfs=GhoSCjIwMjYtMTAtMDdqBRIDRlJBcgUSA0hORBoaEgoyMDI2LTEwLTI4agUSA0hORHIFEgNGUkFAAUgBmAEB&hl=en&curr=EUR",
        "stopsOut": 1,
        "stopsIn": null
      }
    ],
    "flags": {
      "isNewLow": false,
      "priceDeltaEur": -1.0,
      "pctChange7d": 43.9,
      "isBigDrop": false,
      "staleDays": null
    }
  },
  {
    "routeKey": "FRA-NGO-roundtrip",
    "type": "roundtrip",
    "origin": "FRA",
    "destination": "NGO",
    "returnOrigin": null,
    "returnDestination": null,
    "price": 1258.0,
    "source": "googleflights",
    "departDate": "2026-10-28",
    "returnDate": "2026-11-18",
    "nights": 21,
    "airlines": [
      "Finnair"
    ],
    "dealUrl": "https://www.google.com/travel/flights/search?tfs=GhoSCjIwMjYtMTAtMjhqBRIDRlJBcgUSA05HTxoaEgoyMDI2LTExLTE4agUSA05HT3IFEgNGUkFAAUgBmAEB&hl=en&curr=EUR",
    "observedDate": "2026-07-17",
    "segments": {
      "out": [],
      "in": []
    },
    "durationOutMin": null,
    "durationInMin": null,
    "stopsOut": 1,
    "stopsIn": null,
    "scannedPrice": null,
    "alternatives": [
      {
        "price": 1581.0,
        "airlines": [
          "JAL"
        ],
        "source": "googleflights",
        "dealUrl": "https://www.google.com/travel/flights/search?tfs=GhoSCjIwMjYtMTAtMjhqBRIDRlJBcgUSA05HTxoaEgoyMDI2LTExLTE4agUSA05HT3IFEgNGUkFAAUgBmAEB&hl=en&curr=EUR",
        "stopsOut": 1,
        "stopsIn": null
      },
      {
        "price": 1931.0,
        "airlines": [
          "ANA"
        ],
        "source": "googleflights",
        "dealUrl": "https://www.google.com/travel/flights/search?tfs=GhoSCjIwMjYtMTAtMjhqBRIDRlJBcgUSA05HTxoaEgoyMDI2LTExLTE4agUSA05HT3IFEgNGUkFAAUgBmAEB&hl=en&curr=EUR",
        "stopsOut": 1,
        "stopsIn": null
      },
      {
        "price": 2403.0,
        "airlines": [
          "British Airways, JAL"
        ],
        "source": "googleflights",
        "dealUrl": "https://www.google.com/travel/flights/search?tfs=GhoSCjIwMjYtMTAtMjhqBRIDRlJBcgUSA05HTxoaEgoyMDI2LTExLTE4agUSA05HT3IFEgNGUkFAAUgBmAEB&hl=en&curr=EUR",
        "stopsOut": 2,
        "stopsIn": null
      }
    ],
    "flags": {
      "isNewLow": false,
      "priceDeltaEur": -412.0,
      "pctChange7d": 0.5,
      "isBigDrop": true,
      "staleDays": null
    }
  },
  {
    "routeKey": "MUC-KIX-roundtrip",
    "type": "roundtrip",
    "origin": "MUC",
    "destination": "KIX",
    "returnOrigin": null,
    "returnDestination": null,
    "price": 1284.0,
    "source": "googleflights",
    "departDate": "2026-10-07",
    "returnDate": "2026-10-28",
    "nights": 21,
    "airlines": [
      "THAI"
    ],
    "dealUrl": "https://www.google.com/travel/flights/search?tfs=GhoSCjIwMjYtMTAtMDdqBRIDTVVDcgUSA0tJWBoaEgoyMDI2LTEwLTI4agUSA0tJWHIFEgNNVUNAAUgBmAEB&hl=en&curr=EUR",
    "observedDate": "2026-07-17",
    "segments": {
      "out": [],
      "in": []
    },
    "durationOutMin": null,
    "durationInMin": null,
    "stopsOut": 1,
    "stopsIn": null,
    "scannedPrice": null,
    "alternatives": [
      {
        "price": 1403.0,
        "airlines": [
          "THAI"
        ],
        "source": "googleflights",
        "dealUrl": "https://www.google.com/travel/flights/search?tfs=GhoSCjIwMjYtMTAtMDdqBRIDTVVDcgUSA0tJWBoaEgoyMDI2LTEwLTI4agUSA0tJWHIFEgNNVUNAAUgBmAEB&hl=en&curr=EUR",
        "stopsOut": 1,
        "stopsIn": null
      },
      {
        "price": 1424.0,
        "airlines": [
          "Emirates"
        ],
        "source": "googleflights",
        "dealUrl": "https://www.google.com/travel/flights/search?tfs=GhoSCjIwMjYtMTAtMDdqBRIDTVVDcgUSA0tJWBoaEgoyMDI2LTEwLTI4agUSA0tJWHIFEgNNVUNAAUgBmAEB&hl=en&curr=EUR",
        "stopsOut": 1,
        "stopsIn": null
      },
      {
        "price": 1467.0,
        "airlines": [
          "Lufthansa, Cathay Pacific"
        ],
        "source": "googleflights",
        "dealUrl": "https://www.google.com/travel/flights/search?tfs=GhoSCjIwMjYtMTAtMDdqBRIDTVVDcgUSA0tJWBoaEgoyMDI2LTEwLTI4agUSA0tJWHIFEgNNVUNAAUgBmAEB&hl=en&curr=EUR",
        "stopsOut": 2,
        "stopsIn": null
      }
    ],
    "flags": {
      "isNewLow": false,
      "priceDeltaEur": 63.0,
      "pctChange7d": 9.7,
      "isBigDrop": false,
      "staleDays": null
    }
  },
  {
    "routeKey": "MUC-NGO-roundtrip",
    "type": "roundtrip",
    "origin": "MUC",
    "destination": "NGO",
    "returnOrigin": null,
    "returnDestination": null,
    "price": 1523.0,
    "source": "googleflights",
    "departDate": "2026-10-28",
    "returnDate": "2026-11-18",
    "nights": 21,
    "airlines": [
      "Finnair"
    ],
    "dealUrl": "https://www.google.com/travel/flights/search?tfs=GhoSCjIwMjYtMTAtMjhqBRIDTVVDcgUSA05HTxoaEgoyMDI2LTExLTE4agUSA05HT3IFEgNNVUNAAUgBmAEB&hl=en&curr=EUR",
    "observedDate": "2026-07-17",
    "segments": {
      "out": [],
      "in": []
    },
    "durationOutMin": null,
    "durationInMin": null,
    "stopsOut": 1,
    "stopsIn": null,
    "scannedPrice": null,
    "alternatives": [
      {
        "price": 1566.0,
        "airlines": [
          "Lufthansa, ANA"
        ],
        "source": "googleflights",
        "dealUrl": "https://www.google.com/travel/flights/search?tfs=GhoSCjIwMjYtMTAtMjhqBRIDTVVDcgUSA05HTxoaEgoyMDI2LTExLTE4agUSA05HT3IFEgNNVUNAAUgBmAEB&hl=en&curr=EUR",
        "stopsOut": 1,
        "stopsIn": null
      },
      {
        "price": 1790.0,
        "airlines": [
          "ANA"
        ],
        "source": "googleflights",
        "dealUrl": "https://www.google.com/travel/flights/search?tfs=GhoSCjIwMjYtMTAtMjhqBRIDTVVDcgUSA05HTxoaEgoyMDI2LTExLTE4agUSA05HT3IFEgNNVUNAAUgBmAEB&hl=en&curr=EUR",
        "stopsOut": 1,
        "stopsIn": null
      },
      {
        "price": 1928.0,
        "airlines": [
          "Finnair, JAL"
        ],
        "source": "googleflights",
        "dealUrl": "https://www.google.com/travel/flights/search?tfs=GhoSCjIwMjYtMTAtMjhqBRIDTVVDcgUSA05HTxoaEgoyMDI2LTExLTE4agUSA05HT3IFEgNNVUNAAUgBmAEB&hl=en&curr=EUR",
        "stopsOut": 2,
        "stopsIn": null
      }
    ],
    "flags": {
      "isNewLow": false,
      "priceDeltaEur": -94.0,
      "pctChange7d": -19.3,
      "isBigDrop": false,
      "staleDays": null
    }
  },
  {
    "routeKey": "FCO-KIX-roundtrip",
    "type": "roundtrip",
    "origin": "FCO",
    "destination": "KIX",
    "returnOrigin": null,
    "returnDestination": null,
    "price": 660.0,
    "source": "googleflights",
    "departDate": "2026-09-01",
    "returnDate": "2026-09-14",
    "nights": 13,
    "airlines": [],
    "dealUrl": null,
    "observedDate": "2026-06-13",
    "segments": {
      "out": [],
      "in": []
    },
    "durationOutMin": null,
    "durationInMin": null,
    "stopsOut": null,
    "stopsIn": null,
    "scannedPrice": null,
    "alternatives": [],
    "flags": {
      "isNewLow": false,
      "priceDeltaEur": null,
      "pctChange7d": 0.0,
      "isBigDrop": false,
      "staleDays": 34
    }
  },
  {
    "routeKey": "MXP-NGO-KIX-openjaw",
    "type": "openjaw",
    "origin": "MXP",
    "destination": "NGO",
    "returnOrigin": "KIX",
    "returnDestination": "MXP",
    "price": 745.0,
    "source": "serpapi",
    "departDate": "2026-09-01",
    "returnDate": "2026-09-13",
    "nights": 12,
    "airlines": [],
    "dealUrl": null,
    "observedDate": "2026-06-12",
    "segments": {
      "out": [],
      "in": []
    },
    "durationOutMin": null,
    "durationInMin": null,
    "stopsOut": null,
    "stopsIn": null,
    "scannedPrice": null,
    "alternatives": [],
    "flags": {
      "isNewLow": false,
      "priceDeltaEur": null,
      "pctChange7d": 0.0,
      "isBigDrop": false,
      "staleDays": 35
    }
  },
  {
    "routeKey": "MXP-HND-KIX-openjaw",
    "type": "openjaw",
    "origin": "MXP",
    "destination": "HND",
    "returnOrigin": "KIX",
    "returnDestination": "MXP",
    "price": 821.0,
    "source": "serpapi",
    "departDate": "2026-09-01",
    "returnDate": "2026-09-13",
    "nights": 12,
    "airlines": [],
    "dealUrl": null,
    "observedDate": "2026-06-12",
    "segments": {
      "out": [],
      "in": []
    },
    "durationOutMin": null,
    "durationInMin": null,
    "stopsOut": null,
    "stopsIn": null,
    "scannedPrice": null,
    "alternatives": [],
    "flags": {
      "isNewLow": false,
      "priceDeltaEur": null,
      "pctChange7d": 0.0,
      "isBigDrop": false,
      "staleDays": 35
    }
  },
  {
    "routeKey": "MXP-HND-roundtrip",
    "type": "roundtrip",
    "origin": "MXP",
    "destination": "HND",
    "returnOrigin": null,
    "returnDestination": null,
    "price": 821.0,
    "source": "serpapi",
    "departDate": "2026-09-01",
    "returnDate": "2026-09-13",
    "nights": 12,
    "airlines": [],
    "dealUrl": null,
    "observedDate": "2026-06-12",
    "segments": {
      "out": [],
      "in": []
    },
    "durationOutMin": null,
    "durationInMin": null,
    "stopsOut": null,
    "stopsIn": null,
    "scannedPrice": null,
    "alternatives": [],
    "flags": {
      "isNewLow": false,
      "priceDeltaEur": null,
      "pctChange7d": 0.0,
      "isBigDrop": false,
      "staleDays": 35
    }
  },
  {
    "routeKey": "PRG-NRT-roundtrip",
    "type": "roundtrip",
    "origin": "PRG",
    "destination": "NRT",
    "returnOrigin": null,
    "returnDestination": null,
    "price": 838.0,
    "source": "googleflights",
    "departDate": "2026-09-05",
    "returnDate": "2026-09-20",
    "nights": 15,
    "airlines": [],
    "dealUrl": null,
    "observedDate": "2026-06-22",
    "segments": {
      "out": [],
      "in": []
    },
    "durationOutMin": null,
    "durationInMin": null,
    "stopsOut": null,
    "stopsIn": null,
    "scannedPrice": null,
    "alternatives": [],
    "flags": {
      "isNewLow": false,
      "priceDeltaEur": null,
      "pctChange7d": 0.0,
      "isBigDrop": false,
      "staleDays": 25
    }
  },
  {
    "routeKey": "AMS-HND-roundtrip",
    "type": "roundtrip",
    "origin": "AMS",
    "destination": "HND",
    "returnOrigin": null,
    "returnDestination": null,
    "price": 841.0,
    "source": "googleflights",
    "departDate": "2026-11-13",
    "returnDate": "2026-11-30",
    "nights": 17,
    "airlines": [],
    "dealUrl": null,
    "observedDate": "2026-07-05",
    "segments": {
      "out": [],
      "in": []
    },
    "durationOutMin": null,
    "durationInMin": null,
    "stopsOut": null,
    "stopsIn": null,
    "scannedPrice": null,
    "alternatives": [],
    "flags": {
      "isNewLow": false,
      "priceDeltaEur": null,
      "pctChange7d": 0.0,
      "isBigDrop": false,
      "staleDays": 12
    }
  },
  {
    "routeKey": "MXP-KIX-HND-openjaw",
    "type": "openjaw",
    "origin": "MXP",
    "destination": "KIX",
    "returnOrigin": "HND",
    "returnDestination": "MXP",
    "price": 841.0,
    "source": "serpapi",
    "departDate": "2026-09-01",
    "returnDate": "2026-09-13",
    "nights": 12,
    "airlines": [],
    "dealUrl": null,
    "observedDate": "2026-06-12",
    "segments": {
      "out": [],
      "in": []
    },
    "durationOutMin": null,
    "durationInMin": null,
    "stopsOut": null,
    "stopsIn": null,
    "scannedPrice": null,
    "alternatives": [],
    "flags": {
      "isNewLow": false,
      "priceDeltaEur": null,
      "pctChange7d": 0.0,
      "isBigDrop": false,
      "staleDays": 35
    }
  },
  {
    "routeKey": "MXP-KIX-roundtrip",
    "type": "roundtrip",
    "origin": "MXP",
    "destination": "KIX",
    "returnOrigin": null,
    "returnDestination": null,
    "price": 841.0,
    "source": "serpapi",
    "departDate": "2026-09-01",
    "returnDate": "2026-09-13",
    "nights": 12,
    "airlines": [],
    "dealUrl": null,
    "observedDate": "2026-06-12",
    "segments": {
      "out": [],
      "in": []
    },
    "durationOutMin": null,
    "durationInMin": null,
    "stopsOut": null,
    "stopsIn": null,
    "scannedPrice": null,
    "alternatives": [],
    "flags": {
      "isNewLow": false,
      "priceDeltaEur": null,
      "pctChange7d": 0.0,
      "isBigDrop": false,
      "staleDays": 35
    }
  },
  {
    "routeKey": "AMS-NRT-KIX-openjaw",
    "type": "openjaw",
    "origin": "AMS",
    "destination": "NRT",
    "returnOrigin": "KIX",
    "returnDestination": "AMS",
    "price": 855.0,
    "source": "serpapi",
    "departDate": "2026-09-01",
    "returnDate": "2026-09-13",
    "nights": 12,
    "airlines": [],
    "dealUrl": null,
    "observedDate": "2026-06-12",
    "segments": {
      "out": [],
      "in": []
    },
    "durationOutMin": null,
    "durationInMin": null,
    "stopsOut": null,
    "stopsIn": null,
    "scannedPrice": null,
    "alternatives": [],
    "flags": {
      "isNewLow": false,
      "priceDeltaEur": null,
      "pctChange7d": 0.0,
      "isBigDrop": false,
      "staleDays": 35
    }
  },
  {
    "routeKey": "AMS-NGO-KIX-openjaw",
    "type": "openjaw",
    "origin": "AMS",
    "destination": "NGO",
    "returnOrigin": "KIX",
    "returnDestination": "AMS",
    "price": 886.0,
    "source": "serpapi",
    "departDate": "2026-09-01",
    "returnDate": "2026-09-13",
    "nights": 12,
    "airlines": [],
    "dealUrl": null,
    "observedDate": "2026-06-12",
    "segments": {
      "out": [],
      "in": []
    },
    "durationOutMin": null,
    "durationInMin": null,
    "stopsOut": null,
    "stopsIn": null,
    "scannedPrice": null,
    "alternatives": [],
    "flags": {
      "isNewLow": false,
      "priceDeltaEur": null,
      "pctChange7d": 0.0,
      "isBigDrop": false,
      "staleDays": 35
    }
  },
  {
    "routeKey": "AMS-HND-KIX-openjaw",
    "type": "openjaw",
    "origin": "AMS",
    "destination": "HND",
    "returnOrigin": "KIX",
    "returnDestination": "AMS",
    "price": 892.0,
    "source": "serpapi",
    "departDate": "2026-09-01",
    "returnDate": "2026-09-13",
    "nights": 12,
    "airlines": [],
    "dealUrl": null,
    "observedDate": "2026-06-12",
    "segments": {
      "out": [],
      "in": []
    },
    "durationOutMin": null,
    "durationInMin": null,
    "stopsOut": null,
    "stopsIn": null,
    "scannedPrice": null,
    "alternatives": [],
    "flags": {
      "isNewLow": false,
      "priceDeltaEur": null,
      "pctChange7d": 0.0,
      "isBigDrop": false,
      "staleDays": 35
    }
  },
  {
    "routeKey": "MXP-NRT-KIX-openjaw",
    "type": "openjaw",
    "origin": "MXP",
    "destination": "NRT",
    "returnOrigin": "KIX",
    "returnDestination": "MXP",
    "price": 909.0,
    "source": "serpapi",
    "departDate": "2026-09-01",
    "returnDate": "2026-09-13",
    "nights": 12,
    "airlines": [],
    "dealUrl": null,
    "observedDate": "2026-06-12",
    "segments": {
      "out": [],
      "in": []
    },
    "durationOutMin": null,
    "durationInMin": null,
    "stopsOut": null,
    "stopsIn": null,
    "scannedPrice": null,
    "alternatives": [],
    "flags": {
      "isNewLow": false,
      "priceDeltaEur": null,
      "pctChange7d": 0.0,
      "isBigDrop": false,
      "staleDays": 35
    }
  },
  {
    "routeKey": "MXP-NRT-roundtrip",
    "type": "roundtrip",
    "origin": "MXP",
    "destination": "NRT",
    "returnOrigin": null,
    "returnDestination": null,
    "price": 909.0,
    "source": "serpapi",
    "departDate": "2026-09-01",
    "returnDate": "2026-09-13",
    "nights": 12,
    "airlines": [],
    "dealUrl": null,
    "observedDate": "2026-06-12",
    "segments": {
      "out": [],
      "in": []
    },
    "durationOutMin": null,
    "durationInMin": null,
    "stopsOut": null,
    "stopsIn": null,
    "scannedPrice": null,
    "alternatives": [],
    "flags": {
      "isNewLow": false,
      "priceDeltaEur": null,
      "pctChange7d": 0.0,
      "isBigDrop": false,
      "staleDays": 35
    }
  },
  {
    "routeKey": "AMS-NRT-roundtrip",
    "type": "roundtrip",
    "origin": "AMS",
    "destination": "NRT",
    "returnOrigin": null,
    "returnDestination": null,
    "price": 916.0,
    "source": "googleflights",
    "departDate": "2026-11-13",
    "returnDate": "2026-11-30",
    "nights": 17,
    "airlines": [],
    "dealUrl": null,
    "observedDate": "2026-07-05",
    "segments": {
      "out": [],
      "in": []
    },
    "durationOutMin": null,
    "durationInMin": null,
    "stopsOut": null,
    "stopsIn": null,
    "scannedPrice": null,
    "alternatives": [],
    "flags": {
      "isNewLow": false,
      "priceDeltaEur": null,
      "pctChange7d": 0.0,
      "isBigDrop": false,
      "staleDays": 12
    }
  },
  {
    "routeKey": "AMS-KIX-roundtrip",
    "type": "roundtrip",
    "origin": "AMS",
    "destination": "KIX",
    "returnOrigin": null,
    "returnDestination": null,
    "price": 919.0,
    "source": "googleflights",
    "departDate": "2026-11-13",
    "returnDate": "2026-11-30",
    "nights": 17,
    "airlines": [],
    "dealUrl": null,
    "observedDate": "2026-07-05",
    "segments": {
      "out": [],
      "in": []
    },
    "durationOutMin": null,
    "durationInMin": null,
    "stopsOut": null,
    "stopsIn": null,
    "scannedPrice": null,
    "alternatives": [],
    "flags": {
      "isNewLow": false,
      "priceDeltaEur": null,
      "pctChange7d": 0.0,
      "isBigDrop": false,
      "staleDays": 12
    }
  },
  {
    "routeKey": "VIE-NGO-KIX-openjaw",
    "type": "openjaw",
    "origin": "VIE",
    "destination": "NGO",
    "returnOrigin": "KIX",
    "returnDestination": "VIE",
    "price": 941.0,
    "source": "serpapi",
    "departDate": "2026-09-01",
    "returnDate": "2026-09-13",
    "nights": 12,
    "airlines": [],
    "dealUrl": null,
    "observedDate": "2026-06-12",
    "segments": {
      "out": [],
      "in": []
    },
    "durationOutMin": null,
    "durationInMin": null,
    "stopsOut": null,
    "stopsIn": null,
    "scannedPrice": null,
    "alternatives": [],
    "flags": {
      "isNewLow": false,
      "priceDeltaEur": null,
      "pctChange7d": 0.0,
      "isBigDrop": false,
      "staleDays": 35
    }
  },
  {
    "routeKey": "AMS-KIX-HND-openjaw",
    "type": "openjaw",
    "origin": "AMS",
    "destination": "KIX",
    "returnOrigin": "HND",
    "returnDestination": "AMS",
    "price": 943.0,
    "source": "serpapi",
    "departDate": "2026-09-01",
    "returnDate": "2026-09-13",
    "nights": 12,
    "airlines": [],
    "dealUrl": null,
    "observedDate": "2026-06-12",
    "segments": {
      "out": [],
      "in": []
    },
    "durationOutMin": null,
    "durationInMin": null,
    "stopsOut": null,
    "stopsIn": null,
    "scannedPrice": null,
    "alternatives": [],
    "flags": {
      "isNewLow": false,
      "priceDeltaEur": null,
      "pctChange7d": 0.0,
      "isBigDrop": false,
      "staleDays": 35
    }
  },
  {
    "routeKey": "FCO-HND-roundtrip",
    "type": "roundtrip",
    "origin": "FCO",
    "destination": "HND",
    "returnOrigin": null,
    "returnDestination": null,
    "price": 959.0,
    "source": "googleflights",
    "departDate": "2026-09-01",
    "returnDate": "2026-09-14",
    "nights": 13,
    "airlines": [],
    "dealUrl": null,
    "observedDate": "2026-06-13",
    "segments": {
      "out": [],
      "in": []
    },
    "durationOutMin": null,
    "durationInMin": null,
    "stopsOut": null,
    "stopsIn": null,
    "scannedPrice": null,
    "alternatives": [],
    "flags": {
      "isNewLow": false,
      "priceDeltaEur": null,
      "pctChange7d": 0.0,
      "isBigDrop": false,
      "staleDays": 34
    }
  },
  {
    "routeKey": "PRG-NGO-KIX-openjaw",
    "type": "openjaw",
    "origin": "PRG",
    "destination": "NGO",
    "returnOrigin": "KIX",
    "returnDestination": "PRG",
    "price": 982.0,
    "source": "serpapi",
    "departDate": "2026-09-01",
    "returnDate": "2026-09-13",
    "nights": 12,
    "airlines": [],
    "dealUrl": null,
    "observedDate": "2026-06-12",
    "segments": {
      "out": [],
      "in": []
    },
    "durationOutMin": null,
    "durationInMin": null,
    "stopsOut": null,
    "stopsIn": null,
    "scannedPrice": null,
    "alternatives": [],
    "flags": {
      "isNewLow": false,
      "priceDeltaEur": null,
      "pctChange7d": 0.0,
      "isBigDrop": false,
      "staleDays": 35
    }
  },
  {
    "routeKey": "FCO-NRT-roundtrip",
    "type": "roundtrip",
    "origin": "FCO",
    "destination": "NRT",
    "returnOrigin": null,
    "returnDestination": null,
    "price": 991.0,
    "source": "googleflights",
    "departDate": "2026-09-01",
    "returnDate": "2026-09-14",
    "nights": 13,
    "airlines": [],
    "dealUrl": null,
    "observedDate": "2026-06-13",
    "segments": {
      "out": [],
      "in": []
    },
    "durationOutMin": null,
    "durationInMin": null,
    "stopsOut": null,
    "stopsIn": null,
    "scannedPrice": null,
    "alternatives": [],
    "flags": {
      "isNewLow": false,
      "priceDeltaEur": null,
      "pctChange7d": 0.0,
      "isBigDrop": false,
      "staleDays": 34
    }
  },
  {
    "routeKey": "BUD-NRT-roundtrip",
    "type": "roundtrip",
    "origin": "BUD",
    "destination": "NRT",
    "returnOrigin": null,
    "returnDestination": null,
    "price": 1000.0,
    "source": "googleflights",
    "departDate": "2026-09-01",
    "returnDate": "2026-09-13",
    "nights": 12,
    "airlines": [],
    "dealUrl": null,
    "observedDate": "2026-06-24",
    "segments": {
      "out": [],
      "in": []
    },
    "durationOutMin": null,
    "durationInMin": null,
    "stopsOut": null,
    "stopsIn": null,
    "scannedPrice": null,
    "alternatives": [],
    "flags": {
      "isNewLow": false,
      "priceDeltaEur": null,
      "pctChange7d": 0.0,
      "isBigDrop": false,
      "staleDays": 23
    }
  },
  {
    "routeKey": "BUD-NGO-KIX-openjaw",
    "type": "openjaw",
    "origin": "BUD",
    "destination": "NGO",
    "returnOrigin": "KIX",
    "returnDestination": "BUD",
    "price": 1059.0,
    "source": "serpapi",
    "departDate": "2026-09-01",
    "returnDate": "2026-09-13",
    "nights": 12,
    "airlines": [],
    "dealUrl": null,
    "observedDate": "2026-06-12",
    "segments": {
      "out": [],
      "in": []
    },
    "durationOutMin": null,
    "durationInMin": null,
    "stopsOut": null,
    "stopsIn": null,
    "scannedPrice": null,
    "alternatives": [],
    "flags": {
      "isNewLow": false,
      "priceDeltaEur": null,
      "pctChange7d": 0.0,
      "isBigDrop": false,
      "staleDays": 35
    }
  },
  {
    "routeKey": "PRG-HND-roundtrip",
    "type": "roundtrip",
    "origin": "PRG",
    "destination": "HND",
    "returnOrigin": null,
    "returnDestination": null,
    "price": 1101.0,
    "source": "googleflights",
    "departDate": "2026-10-24",
    "returnDate": "2026-11-05",
    "nights": 12,
    "airlines": [],
    "dealUrl": null,
    "observedDate": "2026-06-22",
    "segments": {
      "out": [],
      "in": []
    },
    "durationOutMin": null,
    "durationInMin": null,
    "stopsOut": null,
    "stopsIn": null,
    "scannedPrice": null,
    "alternatives": [],
    "flags": {
      "isNewLow": false,
      "priceDeltaEur": null,
      "pctChange7d": 0.0,
      "isBigDrop": false,
      "staleDays": 25
    }
  },
  {
    "routeKey": "MUC-NGO-KIX-openjaw",
    "type": "openjaw",
    "origin": "MUC",
    "destination": "NGO",
    "returnOrigin": "KIX",
    "returnDestination": "MUC",
    "price": 1107.0,
    "source": "serpapi",
    "departDate": "2026-09-01",
    "returnDate": "2026-09-13",
    "nights": 12,
    "airlines": [],
    "dealUrl": null,
    "observedDate": "2026-06-12",
    "segments": {
      "out": [],
      "in": []
    },
    "durationOutMin": null,
    "durationInMin": null,
    "stopsOut": null,
    "stopsIn": null,
    "scannedPrice": null,
    "alternatives": [],
    "flags": {
      "isNewLow": false,
      "priceDeltaEur": null,
      "pctChange7d": 0.0,
      "isBigDrop": false,
      "staleDays": 35
    }
  },
  {
    "routeKey": "BUD-KIX-roundtrip",
    "type": "roundtrip",
    "origin": "BUD",
    "destination": "KIX",
    "returnOrigin": null,
    "returnDestination": null,
    "price": 1110.0,
    "source": "googleflights",
    "departDate": "2026-12-09",
    "returnDate": "2026-12-27",
    "nights": 18,
    "airlines": [],
    "dealUrl": null,
    "observedDate": "2026-06-24",
    "segments": {
      "out": [],
      "in": []
    },
    "durationOutMin": null,
    "durationInMin": null,
    "stopsOut": null,
    "stopsIn": null,
    "scannedPrice": null,
    "alternatives": [],
    "flags": {
      "isNewLow": false,
      "priceDeltaEur": null,
      "pctChange7d": 0.0,
      "isBigDrop": false,
      "staleDays": 23
    }
  },
  {
    "routeKey": "VIE-NRT-roundtrip",
    "type": "roundtrip",
    "origin": "VIE",
    "destination": "NRT",
    "returnOrigin": null,
    "returnDestination": null,
    "price": 1117.0,
    "source": "googleflights",
    "departDate": "2026-10-21",
    "returnDate": "2026-11-08",
    "nights": 18,
    "airlines": [],
    "dealUrl": null,
    "observedDate": "2026-06-24",
    "segments": {
      "out": [],
      "in": []
    },
    "durationOutMin": null,
    "durationInMin": null,
    "stopsOut": null,
    "stopsIn": null,
    "scannedPrice": null,
    "alternatives": [],
    "flags": {
      "isNewLow": false,
      "priceDeltaEur": null,
      "pctChange7d": 0.0,
      "isBigDrop": false,
      "staleDays": 23
    }
  },
  {
    "routeKey": "PRG-KIX-roundtrip",
    "type": "roundtrip",
    "origin": "PRG",
    "destination": "KIX",
    "returnOrigin": null,
    "returnDestination": null,
    "price": 1133.0,
    "source": "googleflights",
    "departDate": "2026-10-24",
    "returnDate": "2026-11-05",
    "nights": 12,
    "airlines": [],
    "dealUrl": null,
    "observedDate": "2026-06-22",
    "segments": {
      "out": [],
      "in": []
    },
    "durationOutMin": null,
    "durationInMin": null,
    "stopsOut": null,
    "stopsIn": null,
    "scannedPrice": null,
    "alternatives": [],
    "flags": {
      "isNewLow": false,
      "priceDeltaEur": null,
      "pctChange7d": 0.0,
      "isBigDrop": false,
      "staleDays": 25
    }
  },
  {
    "routeKey": "BUD-HND-roundtrip",
    "type": "roundtrip",
    "origin": "BUD",
    "destination": "HND",
    "returnOrigin": null,
    "returnDestination": null,
    "price": 1139.0,
    "source": "googleflights",
    "departDate": "2026-12-09",
    "returnDate": "2026-12-27",
    "nights": 18,
    "airlines": [],
    "dealUrl": null,
    "observedDate": "2026-06-24",
    "segments": {
      "out": [],
      "in": []
    },
    "durationOutMin": null,
    "durationInMin": null,
    "stopsOut": null,
    "stopsIn": null,
    "scannedPrice": null,
    "alternatives": [],
    "flags": {
      "isNewLow": false,
      "priceDeltaEur": null,
      "pctChange7d": 0.0,
      "isBigDrop": false,
      "staleDays": 23
    }
  },
  {
    "routeKey": "AMS-ITM-HND-openjaw",
    "type": "openjaw",
    "origin": "AMS",
    "destination": "ITM",
    "returnOrigin": "HND",
    "returnDestination": "AMS",
    "price": 1144.0,
    "source": "serpapi",
    "departDate": "2026-09-01",
    "returnDate": "2026-09-13",
    "nights": 12,
    "airlines": [],
    "dealUrl": null,
    "observedDate": "2026-06-12",
    "segments": {
      "out": [],
      "in": []
    },
    "durationOutMin": null,
    "durationInMin": null,
    "stopsOut": null,
    "stopsIn": null,
    "scannedPrice": null,
    "alternatives": [],
    "flags": {
      "isNewLow": false,
      "priceDeltaEur": null,
      "pctChange7d": 0.0,
      "isBigDrop": false,
      "staleDays": 35
    }
  },
  {
    "routeKey": "VIE-KIX-roundtrip",
    "type": "roundtrip",
    "origin": "VIE",
    "destination": "KIX",
    "returnOrigin": null,
    "returnDestination": null,
    "price": 1150.0,
    "source": "googleflights",
    "departDate": "2026-10-21",
    "returnDate": "2026-11-08",
    "nights": 18,
    "airlines": [],
    "dealUrl": null,
    "observedDate": "2026-06-24",
    "segments": {
      "out": [],
      "in": []
    },
    "durationOutMin": null,
    "durationInMin": null,
    "stopsOut": null,
    "stopsIn": null,
    "scannedPrice": null,
    "alternatives": [],
    "flags": {
      "isNewLow": false,
      "priceDeltaEur": null,
      "pctChange7d": 0.0,
      "isBigDrop": false,
      "staleDays": 23
    }
  },
  {
    "routeKey": "VIE-NGO-roundtrip",
    "type": "roundtrip",
    "origin": "VIE",
    "destination": "NGO",
    "returnOrigin": null,
    "returnDestination": null,
    "price": 1156.0,
    "source": "googleflights",
    "departDate": "2026-12-09",
    "returnDate": "2026-12-27",
    "nights": 18,
    "airlines": [],
    "dealUrl": null,
    "observedDate": "2026-06-24",
    "segments": {
      "out": [],
      "in": []
    },
    "durationOutMin": null,
    "durationInMin": null,
    "stopsOut": null,
    "stopsIn": null,
    "scannedPrice": null,
    "alternatives": [],
    "flags": {
      "isNewLow": false,
      "priceDeltaEur": null,
      "pctChange7d": 0.0,
      "isBigDrop": false,
      "staleDays": 23
    }
  },
  {
    "routeKey": "NUE-KIX-HND-openjaw",
    "type": "openjaw",
    "origin": "NUE",
    "destination": "KIX",
    "returnOrigin": "HND",
    "returnDestination": "NUE",
    "price": 1169.0,
    "source": "serpapi",
    "departDate": "2026-09-01",
    "returnDate": "2026-09-13",
    "nights": 12,
    "airlines": [],
    "dealUrl": null,
    "observedDate": "2026-06-12",
    "segments": {
      "out": [],
      "in": []
    },
    "durationOutMin": null,
    "durationInMin": null,
    "stopsOut": null,
    "stopsIn": null,
    "scannedPrice": null,
    "alternatives": [],
    "flags": {
      "isNewLow": false,
      "priceDeltaEur": null,
      "pctChange7d": 0.0,
      "isBigDrop": false,
      "staleDays": 35
    }
  },
  {
    "routeKey": "FRA-ITM-roundtrip",
    "type": "roundtrip",
    "origin": "FRA",
    "destination": "ITM",
    "returnOrigin": null,
    "returnDestination": null,
    "price": 1175.0,
    "source": "googleflights",
    "departDate": "2026-11-13",
    "returnDate": "2026-11-30",
    "nights": 17,
    "airlines": [],
    "dealUrl": null,
    "observedDate": "2026-07-05",
    "segments": {
      "out": [],
      "in": []
    },
    "durationOutMin": null,
    "durationInMin": null,
    "stopsOut": null,
    "stopsIn": null,
    "scannedPrice": null,
    "alternatives": [],
    "flags": {
      "isNewLow": false,
      "priceDeltaEur": null,
      "pctChange7d": 0.0,
      "isBigDrop": false,
      "staleDays": 12
    }
  },
  {
    "routeKey": "VIE-HND-roundtrip",
    "type": "roundtrip",
    "origin": "VIE",
    "destination": "HND",
    "returnOrigin": null,
    "returnDestination": null,
    "price": 1175.0,
    "source": "googleflights",
    "departDate": "2026-10-21",
    "returnDate": "2026-11-08",
    "nights": 18,
    "airlines": [],
    "dealUrl": null,
    "observedDate": "2026-06-24",
    "segments": {
      "out": [],
      "in": []
    },
    "durationOutMin": null,
    "durationInMin": null,
    "stopsOut": null,
    "stopsIn": null,
    "scannedPrice": null,
    "alternatives": [],
    "flags": {
      "isNewLow": false,
      "priceDeltaEur": null,
      "pctChange7d": 0.0,
      "isBigDrop": false,
      "staleDays": 23
    }
  },
  {
    "routeKey": "PRG-NGO-roundtrip",
    "type": "roundtrip",
    "origin": "PRG",
    "destination": "NGO",
    "returnOrigin": null,
    "returnDestination": null,
    "price": 1203.0,
    "source": "googleflights",
    "departDate": "2026-09-05",
    "returnDate": "2026-09-20",
    "nights": 15,
    "airlines": [],
    "dealUrl": null,
    "observedDate": "2026-06-22",
    "segments": {
      "out": [],
      "in": []
    },
    "durationOutMin": null,
    "durationInMin": null,
    "stopsOut": null,
    "stopsIn": null,
    "scannedPrice": null,
    "alternatives": [],
    "flags": {
      "isNewLow": false,
      "priceDeltaEur": null,
      "pctChange7d": 0.0,
      "isBigDrop": false,
      "staleDays": 25
    }
  },
  {
    "routeKey": "MXP-ITM-HND-openjaw",
    "type": "openjaw",
    "origin": "MXP",
    "destination": "ITM",
    "returnOrigin": "HND",
    "returnDestination": "MXP",
    "price": 1213.0,
    "source": "serpapi",
    "departDate": "2026-09-01",
    "returnDate": "2026-09-13",
    "nights": 12,
    "airlines": [],
    "dealUrl": null,
    "observedDate": "2026-06-12",
    "segments": {
      "out": [],
      "in": []
    },
    "durationOutMin": null,
    "durationInMin": null,
    "stopsOut": null,
    "stopsIn": null,
    "scannedPrice": null,
    "alternatives": [],
    "flags": {
      "isNewLow": false,
      "priceDeltaEur": null,
      "pctChange7d": 0.0,
      "isBigDrop": false,
      "staleDays": 35
    }
  },
  {
    "routeKey": "AMS-ITM-roundtrip",
    "type": "roundtrip",
    "origin": "AMS",
    "destination": "ITM",
    "returnOrigin": null,
    "returnDestination": null,
    "price": 1215.0,
    "source": "googleflights",
    "departDate": "2026-11-13",
    "returnDate": "2026-11-30",
    "nights": 17,
    "airlines": [],
    "dealUrl": null,
    "observedDate": "2026-07-05",
    "segments": {
      "out": [],
      "in": []
    },
    "durationOutMin": null,
    "durationInMin": null,
    "stopsOut": null,
    "stopsIn": null,
    "scannedPrice": null,
    "alternatives": [],
    "flags": {
      "isNewLow": false,
      "priceDeltaEur": null,
      "pctChange7d": 0.0,
      "isBigDrop": false,
      "staleDays": 12
    }
  },
  {
    "routeKey": "MXP-ITM-roundtrip",
    "type": "roundtrip",
    "origin": "MXP",
    "destination": "ITM",
    "returnOrigin": null,
    "returnDestination": null,
    "price": 1231.0,
    "source": "googleflights",
    "departDate": "2026-09-01",
    "returnDate": "2026-09-13",
    "nights": 12,
    "airlines": [],
    "dealUrl": null,
    "observedDate": "2026-06-12",
    "segments": {
      "out": [],
      "in": []
    },
    "durationOutMin": null,
    "durationInMin": null,
    "stopsOut": null,
    "stopsIn": null,
    "scannedPrice": null,
    "alternatives": [],
    "flags": {
      "isNewLow": false,
      "priceDeltaEur": null,
      "pctChange7d": 0.0,
      "isBigDrop": false,
      "staleDays": 35
    }
  },
  {
    "routeKey": "NUE-HND-KIX-openjaw",
    "type": "openjaw",
    "origin": "NUE",
    "destination": "HND",
    "returnOrigin": "KIX",
    "returnDestination": "NUE",
    "price": 1247.0,
    "source": "serpapi",
    "departDate": "2026-09-01",
    "returnDate": "2026-09-13",
    "nights": 12,
    "airlines": [],
    "dealUrl": null,
    "observedDate": "2026-06-12",
    "segments": {
      "out": [],
      "in": []
    },
    "durationOutMin": null,
    "durationInMin": null,
    "stopsOut": null,
    "stopsIn": null,
    "scannedPrice": null,
    "alternatives": [],
    "flags": {
      "isNewLow": false,
      "priceDeltaEur": null,
      "pctChange7d": 0.0,
      "isBigDrop": false,
      "staleDays": 35
    }
  },
  {
    "routeKey": "FMM-KIX-roundtrip",
    "type": "roundtrip",
    "origin": "FMM",
    "destination": "KIX",
    "returnOrigin": null,
    "returnDestination": null,
    "price": 1253.0,
    "source": "flightlabs",
    "departDate": "2026-09-04",
    "returnDate": "2026-09-21",
    "nights": 17,
    "airlines": [],
    "dealUrl": null,
    "observedDate": "2026-06-23",
    "segments": {
      "out": [],
      "in": []
    },
    "durationOutMin": null,
    "durationInMin": null,
    "stopsOut": null,
    "stopsIn": null,
    "scannedPrice": null,
    "alternatives": [],
    "flags": {
      "isNewLow": false,
      "priceDeltaEur": null,
      "pctChange7d": 0.0,
      "isBigDrop": false,
      "staleDays": 24
    }
  },
  {
    "routeKey": "NUE-NRT-KIX-openjaw",
    "type": "openjaw",
    "origin": "NUE",
    "destination": "NRT",
    "returnOrigin": "KIX",
    "returnDestination": "NUE",
    "price": 1292.0,
    "source": "serpapi",
    "departDate": "2026-09-01",
    "returnDate": "2026-09-13",
    "nights": 12,
    "airlines": [],
    "dealUrl": null,
    "observedDate": "2026-06-12",
    "segments": {
      "out": [],
      "in": []
    },
    "durationOutMin": null,
    "durationInMin": null,
    "stopsOut": null,
    "stopsIn": null,
    "scannedPrice": null,
    "alternatives": [],
    "flags": {
      "isNewLow": false,
      "priceDeltaEur": null,
      "pctChange7d": 0.0,
      "isBigDrop": false,
      "staleDays": 35
    }
  },
  {
    "routeKey": "NUE-NGO-KIX-openjaw",
    "type": "openjaw",
    "origin": "NUE",
    "destination": "NGO",
    "returnOrigin": "KIX",
    "returnDestination": "NUE",
    "price": 1329.0,
    "source": "serpapi",
    "departDate": "2026-09-01",
    "returnDate": "2026-09-13",
    "nights": 12,
    "airlines": [],
    "dealUrl": null,
    "observedDate": "2026-06-12",
    "segments": {
      "out": [],
      "in": []
    },
    "durationOutMin": null,
    "durationInMin": null,
    "stopsOut": null,
    "stopsIn": null,
    "scannedPrice": null,
    "alternatives": [],
    "flags": {
      "isNewLow": false,
      "priceDeltaEur": null,
      "pctChange7d": 0.0,
      "isBigDrop": false,
      "staleDays": 35
    }
  },
  {
    "routeKey": "BUD-NGO-roundtrip",
    "type": "roundtrip",
    "origin": "BUD",
    "destination": "NGO",
    "returnOrigin": null,
    "returnDestination": null,
    "price": 1331.0,
    "source": "googleflights",
    "departDate": "2026-12-09",
    "returnDate": "2026-12-27",
    "nights": 18,
    "airlines": [],
    "dealUrl": null,
    "observedDate": "2026-06-24",
    "segments": {
      "out": [],
      "in": []
    },
    "durationOutMin": null,
    "durationInMin": null,
    "stopsOut": null,
    "stopsIn": null,
    "scannedPrice": null,
    "alternatives": [],
    "flags": {
      "isNewLow": false,
      "priceDeltaEur": null,
      "pctChange7d": 0.0,
      "isBigDrop": false,
      "staleDays": 23
    }
  },
  {
    "routeKey": "NUE-NRT-roundtrip",
    "type": "roundtrip",
    "origin": "NUE",
    "destination": "NRT",
    "returnOrigin": null,
    "returnDestination": null,
    "price": 1342.0,
    "source": "googleflights",
    "departDate": "2026-09-01",
    "returnDate": "2026-09-13",
    "nights": 12,
    "airlines": [],
    "dealUrl": null,
    "observedDate": "2026-06-12",
    "segments": {
      "out": [],
      "in": []
    },
    "durationOutMin": null,
    "durationInMin": null,
    "stopsOut": null,
    "stopsIn": null,
    "scannedPrice": null,
    "alternatives": [],
    "flags": {
      "isNewLow": false,
      "priceDeltaEur": null,
      "pctChange7d": 0.0,
      "isBigDrop": false,
      "staleDays": 35
    }
  },
  {
    "routeKey": "NUE-HND-roundtrip",
    "type": "roundtrip",
    "origin": "NUE",
    "destination": "HND",
    "returnOrigin": null,
    "returnDestination": null,
    "price": 1357.0,
    "source": "googleflights",
    "departDate": "2026-09-01",
    "returnDate": "2026-09-13",
    "nights": 12,
    "airlines": [],
    "dealUrl": null,
    "observedDate": "2026-06-12",
    "segments": {
      "out": [],
      "in": []
    },
    "durationOutMin": null,
    "durationInMin": null,
    "stopsOut": null,
    "stopsIn": null,
    "scannedPrice": null,
    "alternatives": [],
    "flags": {
      "isNewLow": false,
      "priceDeltaEur": null,
      "pctChange7d": 0.0,
      "isBigDrop": false,
      "staleDays": 35
    }
  },
  {
    "routeKey": "NUE-ITM-HND-openjaw",
    "type": "openjaw",
    "origin": "NUE",
    "destination": "ITM",
    "returnOrigin": "HND",
    "returnDestination": "NUE",
    "price": 1368.0,
    "source": "serpapi",
    "departDate": "2026-09-01",
    "returnDate": "2026-09-13",
    "nights": 12,
    "airlines": [],
    "dealUrl": null,
    "observedDate": "2026-06-12",
    "segments": {
      "out": [],
      "in": []
    },
    "durationOutMin": null,
    "durationInMin": null,
    "stopsOut": null,
    "stopsIn": null,
    "scannedPrice": null,
    "alternatives": [],
    "flags": {
      "isNewLow": false,
      "priceDeltaEur": null,
      "pctChange7d": 0.0,
      "isBigDrop": false,
      "staleDays": 35
    }
  }
]
